{
	"chain_id": "dif_com_2",
	"task": {
		"task_id": "dif_com",
		"n_chains": 10,
		"max_gens": 9,
		"sound_change_freq": 0,
		"stop_on_convergence": false,
		"n_shapes": 3,
		"n_colors": 3,
		"bottleneck": 6,
		"mini_test_freq": 3,
		"training_reps": 6,
		"test_reps": 1,
		"communication": true,
		"stems": [
			"buvi",
			"zeti",
			"wopi"
		],
		"seed_suffix_system": "holistic_random",
		"seed_suffix_spellings": [
			[
				"c",
				"k",
				"q"
			],
			[
				"oe",
				"o",
				"oh"
			]
		],
		"return_url": "https://app.prolific.co/submissions/complete?cc=CSA91ZMA"
	},
	"status": "completed",
	"current_gen": 9,
	"sound_epoch": 0,
	"subject_a": null,
	"subject_b": null,
	"subjects": [
		[
			"060",
			"076"
		],
		[
			"105",
			"111"
		],
		[
			"185",
			"181"
		],
		[
			"238",
			"233"
		],
		[
			"337",
			"327"
		],
		[
			"350",
			"354"
		],
		[
			"416",
			"404"
		],
		[
			"475",
			"468"
		],
		[
			"493",
			"508"
		]
	],
	"lexicon": {
		"0_0": "buvicogh",
		"0_1": "buvikogh",
		"0_2": "buvigoeg",
		"1_0": "zeticogh",
		"1_1": "zeticogh",
		"1_2": "zeticogh",
		"2_0": "wopicogh",
		"2_1": "wopicogh",
		"2_2": "wopikoeg"
	},
	"spoken_forms": [
		{
			"0_0": "0.m4a",
			"0_1": "0.m4a",
			"0_2": "0.m4a",
			"1_0": "1.m4a",
			"1_1": "1.m4a",
			"1_2": "1.m4a",
			"2_0": "2.m4a",
			"2_1": "2.m4a",
			"2_2": "2.m4a"
		}
	]
}