{
	"subject_id": "011",
	"client_id": null,
	"creation_time": 1687864702,
	"modified_time": 1687866219,
	"status": "approved",
	"chain_id": "com_1",
	"generation": 1,
	"input_lexicon": {
		"0_0": "buvixu",
		"0_1": "buviso",
		"0_2": "buvishe",
		"0_3": "buvitha",
		"1_0": "zetixu",
		"1_1": "zetiso",
		"1_2": "zetishe",
		"1_3": "zetitha",
		"2_0": "gafixu",
		"2_1": "gafiso",
		"2_2": "gafishe",
		"2_3": "gafitha",
		"3_0": "wopixu",
		"3_1": "wopiso",
		"3_2": "wopishe",
		"3_3": "wopitha"
	},
	"spoken_forms": {
		"0_0": "0_3_3.m4a",
		"0_1": "0_1_2.m4a",
		"0_2": "0_2_1.m4a",
		"0_3": "0_0_0.m4a",
		"1_0": "1_3_3.m4a",
		"1_1": "1_1_2.m4a",
		"1_2": "1_2_1.m4a",
		"1_3": "1_0_0.m4a",
		"2_0": "2_3_3.m4a",
		"2_1": "2_1_2.m4a",
		"2_2": "2_2_1.m4a",
		"2_3": "2_0_0.m4a",
		"3_0": "3_3_3.m4a",
		"3_1": "3_1_2.m4a",
		"3_2": "3_2_1.m4a",
		"3_3": "3_0_0.m4a"
	},
	"training_items": [
		"3_3",
		"3_1",
		"2_1",
		"1_0",
		"1_1",
		"3_2",
		"2_0",
		"2_2",
		"0_0",
		"1_2",
		"3_0",
		"2_3"
	],
	"trial_sequence": [
		{
			"event": "consent",
			"payload": {
				"progress": 0
			}
		},
		{
			"event": "instructions",
			"payload": {
				"instruction_screen": "training",
				"instruction_time": 5000,
				"response_kind": "ready_to_assign",
				"progress": 0
			}
		},
		{
			"event": "instructions",
			"payload": {
				"instruction_screen": "training_for_communication",
				"instruction_time": 5000,
				"response_kind": "next",
				"progress": 0
			}
		},
		{
			"event": "training_block",
			"payload": {
				"training_trials": [
					{
						"item": "1_1",
						"word": "zetiso",
						"shape": "1",
						"color": "1"
					},
					{
						"item": "1_0",
						"word": "zetixu",
						"shape": "1",
						"color": "0"
					},
					{
						"item": "3_1",
						"word": "wopiso",
						"shape": "3",
						"color": "1"
					},
					{
						"item": "3_2",
						"word": "wopishe",
						"shape": "3",
						"color": "2"
					}
				],
				"test_trial": {
					"item": "1_0",
					"word": "zetixu",
					"shape": "1",
					"color": "0",
					"catch_trial": false,
					"max_response_time": 20000
				},
				"exposure_time": 2000,
				"pause_time": 500,
				"progress": 0.0364963503649635
			}
		},
		{
			"event": "training_block",
			"payload": {
				"training_trials": [
					{
						"item": "3_3",
						"word": "wopitha",
						"shape": "3",
						"color": "3"
					},
					{
						"item": "1_2",
						"word": "zetishe",
						"shape": "1",
						"color": "2"
					},
					{
						"item": "2_0",
						"word": "gafixu",
						"shape": "2",
						"color": "0"
					},
					{
						"item": "0_0",
						"word": "buvixu",
						"shape": "0",
						"color": "0"
					}
				],
				"test_trial": {
					"item": "0_0",
					"word": "buvixu",
					"shape": "0",
					"color": "0",
					"catch_trial": false,
					"max_response_time": 20000
				},
				"exposure_time": 2000,
				"pause_time": 500,
				"progress": 0.05474452554744526
			}
		},
		{
			"event": "training_block",
			"payload": {
				"training_trials": [
					{
						"item": "2_3",
						"word": "gafitha",
						"shape": "2",
						"color": "3"
					},
					{
						"item": "2_1",
						"word": "gafiso",
						"shape": "2",
						"color": "1"
					},
					{
						"item": "2_2",
						"word": "gafishe",
						"shape": "2",
						"color": "2"
					},
					{
						"item": "3_0",
						"word": "wopixu",
						"shape": "3",
						"color": "0"
					}
				],
				"test_trial": {
					"item": "2_3",
					"word": "gafitha",
					"shape": "2",
					"color": "3",
					"catch_trial": false,
					"max_response_time": 20000
				},
				"exposure_time": 2000,
				"pause_time": 500,
				"progress": 0.072992700729927
			}
		},
		{
			"event": "training_block",
			"payload": {
				"training_trials": [
					{
						"item": "1_2",
						"word": "zetishe",
						"shape": "1",
						"color": "2"
					},
					{
						"item": "0_0",
						"word": "buvixu",
						"shape": "0",
						"color": "0"
					},
					{
						"item": "3_2",
						"word": "wopishe",
						"shape": "3",
						"color": "2"
					},
					{
						"item": "2_0",
						"word": "gafixu",
						"shape": "2",
						"color": "0"
					}
				],
				"test_trial": {
					"item": "1_2",
					"word": "zetishe",
					"shape": "1",
					"color": "2",
					"catch_trial": false,
					"max_response_time": 20000
				},
				"exposure_time": 2000,
				"pause_time": 500,
				"progress": 0.09124087591240876
			}
		},
		{
			"event": "training_block",
			"payload": {
				"training_trials": [
					{
						"item": "2_2",
						"word": "gafishe",
						"shape": "2",
						"color": "2"
					},
					{
						"item": "2_1",
						"word": "gafiso",
						"shape": "2",
						"color": "1"
					},
					{
						"item": "1_1",
						"word": "zetiso",
						"shape": "1",
						"color": "1"
					},
					{
						"item": "3_3",
						"word": "wopitha",
						"shape": "3",
						"color": "3"
					}
				],
				"test_trial": {
					"item": "2_1",
					"word": "gafiso",
					"shape": "2",
					"color": "1",
					"catch_trial": false,
					"max_response_time": 20000
				},
				"exposure_time": 2000,
				"pause_time": 500,
				"progress": 0.10948905109489052
			}
		},
		{
			"event": "training_block",
			"payload": {
				"training_trials": [
					{
						"item": "3_0",
						"word": "wopixu",
						"shape": "3",
						"color": "0"
					},
					{
						"item": "1_0",
						"word": "zetixu",
						"shape": "1",
						"color": "0"
					},
					{
						"item": "2_3",
						"word": "gafitha",
						"shape": "2",
						"color": "3"
					},
					{
						"item": "3_1",
						"word": "wopiso",
						"shape": "3",
						"color": "1"
					}
				],
				"test_trial": {
					"item": "3_2",
					"word": "wopishe",
					"shape": "3",
					"color": "2",
					"catch_trial": false,
					"max_response_time": 20000
				},
				"exposure_time": 2000,
				"pause_time": 500,
				"progress": 0.12773722627737227
			}
		},
		{
			"event": "training_block",
			"payload": {
				"training_trials": [
					{
						"item": "3_0",
						"word": "wopixu",
						"shape": "3",
						"color": "0"
					},
					{
						"item": "2_0",
						"word": "gafixu",
						"shape": "2",
						"color": "0"
					},
					{
						"item": "2_1",
						"word": "gafiso",
						"shape": "2",
						"color": "1"
					},
					{
						"item": "3_2",
						"word": "wopishe",
						"shape": "3",
						"color": "2"
					}
				],
				"test_trial": {
					"item": "3_3",
					"word": "wopitha",
					"shape": "3",
					"color": "3",
					"catch_trial": false,
					"max_response_time": 20000
				},
				"exposure_time": 2000,
				"pause_time": 500,
				"progress": 0.145985401459854
			}
		},
		{
			"event": "training_block",
			"payload": {
				"training_trials": [
					{
						"item": "3_1",
						"word": "wopiso",
						"shape": "3",
						"color": "1"
					},
					{
						"item": "1_0",
						"word": "zetixu",
						"shape": "1",
						"color": "0"
					},
					{
						"item": "1_2",
						"word": "zetishe",
						"shape": "1",
						"color": "2"
					},
					{
						"item": "0_0",
						"word": "buvixu",
						"shape": "0",
						"color": "0"
					}
				],
				"test_trial": {
					"item": "1_1",
					"word": "zetiso",
					"shape": "1",
					"color": "1",
					"catch_trial": false,
					"max_response_time": 20000
				},
				"exposure_time": 2000,
				"pause_time": 500,
				"progress": 0.16423357664233576
			}
		},
		{
			"event": "training_block",
			"payload": {
				"training_trials": [
					{
						"item": "3_3",
						"word": "wopitha",
						"shape": "3",
						"color": "3"
					},
					{
						"item": "1_1",
						"word": "zetiso",
						"shape": "1",
						"color": "1"
					},
					{
						"item": "2_2",
						"word": "gafishe",
						"shape": "2",
						"color": "2"
					},
					{
						"item": "2_3",
						"word": "gafitha",
						"shape": "2",
						"color": "3"
					}
				],
				"test_trial": {
					"item": "2_0",
					"word": "gafixu",
					"shape": "2",
					"color": "0",
					"catch_trial": false,
					"max_response_time": 20000
				},
				"exposure_time": 2000,
				"pause_time": 500,
				"progress": 0.18248175182481752
			}
		},
		{
			"event": "training_block",
			"payload": {
				"training_trials": [
					{
						"item": "3_2",
						"word": "wopishe",
						"shape": "3",
						"color": "2"
					},
					{
						"item": "1_2",
						"word": "zetishe",
						"shape": "1",
						"color": "2"
					},
					{
						"item": "3_3",
						"word": "wopitha",
						"shape": "3",
						"color": "3"
					},
					{
						"item": "1_1",
						"word": "zetiso",
						"shape": "1",
						"color": "1"
					}
				],
				"test_trial": {
					"item": "2_2",
					"word": "gafishe",
					"shape": "2",
					"color": "2",
					"catch_trial": false,
					"max_response_time": 20000
				},
				"exposure_time": 2000,
				"pause_time": 500,
				"progress": 0.20072992700729927
			}
		},
		{
			"event": "training_block",
			"payload": {
				"training_trials": [
					{
						"item": "2_1",
						"word": "gafiso",
						"shape": "2",
						"color": "1"
					},
					{
						"item": "3_0",
						"word": "wopixu",
						"shape": "3",
						"color": "0"
					},
					{
						"item": "2_3",
						"word": "gafitha",
						"shape": "2",
						"color": "3"
					},
					{
						"item": "3_1",
						"word": "wopiso",
						"shape": "3",
						"color": "1"
					}
				],
				"test_trial": {
					"item": "3_0",
					"word": "wopixu",
					"shape": "3",
					"color": "0",
					"catch_trial": true,
					"max_response_time": 20000
				},
				"exposure_time": 2000,
				"pause_time": 500,
				"progress": 0.21897810218978103
			}
		},
		{
			"event": "training_block",
			"payload": {
				"training_trials": [
					{
						"item": "0_0",
						"word": "buvixu",
						"shape": "0",
						"color": "0"
					},
					{
						"item": "2_0",
						"word": "gafixu",
						"shape": "2",
						"color": "0"
					},
					{
						"item": "1_0",
						"word": "zetixu",
						"shape": "1",
						"color": "0"
					},
					{
						"item": "2_2",
						"word": "gafishe",
						"shape": "2",
						"color": "2"
					}
				],
				"test_trial": {
					"item": "3_1",
					"word": "wopiso",
					"shape": "3",
					"color": "1",
					"catch_trial": false,
					"max_response_time": 20000
				},
				"exposure_time": 2000,
				"pause_time": 500,
				"progress": 0.23722627737226276
			}
		},
		{
			"event": "training_block",
			"payload": {
				"training_trials": [
					{
						"item": "1_2",
						"word": "zetishe",
						"shape": "1",
						"color": "2"
					},
					{
						"item": "3_0",
						"word": "wopixu",
						"shape": "3",
						"color": "0"
					},
					{
						"item": "3_1",
						"word": "wopiso",
						"shape": "3",
						"color": "1"
					},
					{
						"item": "3_2",
						"word": "wopishe",
						"shape": "3",
						"color": "2"
					}
				],
				"test_trial": {
					"item": "1_2",
					"word": "zetishe",
					"shape": "1",
					"color": "2",
					"catch_trial": false,
					"max_response_time": 20000
				},
				"exposure_time": 2000,
				"pause_time": 500,
				"progress": 0.25547445255474455
			}
		},
		{
			"event": "training_block",
			"payload": {
				"training_trials": [
					{
						"item": "1_1",
						"word": "zetiso",
						"shape": "1",
						"color": "1"
					},
					{
						"item": "2_2",
						"word": "gafishe",
						"shape": "2",
						"color": "2"
					},
					{
						"item": "0_0",
						"word": "buvixu",
						"shape": "0",
						"color": "0"
					},
					{
						"item": "2_0",
						"word": "gafixu",
						"shape": "2",
						"color": "0"
					}
				],
				"test_trial": {
					"item": "1_1",
					"word": "zetiso",
					"shape": "1",
					"color": "1",
					"catch_trial": false,
					"max_response_time": 20000
				},
				"exposure_time": 2000,
				"pause_time": 500,
				"progress": 0.2737226277372263
			}
		},
		{
			"event": "training_block",
			"payload": {
				"training_trials": [
					{
						"item": "3_3",
						"word": "wopitha",
						"shape": "3",
						"color": "3"
					},
					{
						"item": "2_3",
						"word": "gafitha",
						"shape": "2",
						"color": "3"
					},
					{
						"item": "2_1",
						"word": "gafiso",
						"shape": "2",
						"color": "1"
					},
					{
						"item": "1_0",
						"word": "zetixu",
						"shape": "1",
						"color": "0"
					}
				],
				"test_trial": {
					"item": "3_0",
					"word": "wopixu",
					"shape": "3",
					"color": "0",
					"catch_trial": false,
					"max_response_time": 20000
				},
				"exposure_time": 2000,
				"pause_time": 500,
				"progress": 0.291970802919708
			}
		},
		{
			"event": "training_block",
			"payload": {
				"training_trials": [
					{
						"item": "3_1",
						"word": "wopiso",
						"shape": "3",
						"color": "1"
					},
					{
						"item": "0_0",
						"word": "buvixu",
						"shape": "0",
						"color": "0"
					},
					{
						"item": "2_0",
						"word": "gafixu",
						"shape": "2",
						"color": "0"
					},
					{
						"item": "2_3",
						"word": "gafitha",
						"shape": "2",
						"color": "3"
					}
				],
				"test_trial": {
					"item": "2_3",
					"word": "gafitha",
					"shape": "2",
					"color": "3",
					"catch_trial": false,
					"max_response_time": 20000
				},
				"exposure_time": 2000,
				"pause_time": 500,
				"progress": 0.3102189781021898
			}
		},
		{
			"event": "training_block",
			"payload": {
				"training_trials": [
					{
						"item": "2_1",
						"word": "gafiso",
						"shape": "2",
						"color": "1"
					},
					{
						"item": "3_2",
						"word": "wopishe",
						"shape": "3",
						"color": "2"
					},
					{
						"item": "1_1",
						"word": "zetiso",
						"shape": "1",
						"color": "1"
					},
					{
						"item": "3_3",
						"word": "wopitha",
						"shape": "3",
						"color": "3"
					}
				],
				"test_trial": {
					"item": "0_0",
					"word": "buvixu",
					"shape": "0",
					"color": "0",
					"catch_trial": false,
					"max_response_time": 20000
				},
				"exposure_time": 2000,
				"pause_time": 500,
				"progress": 0.3284671532846715
			}
		},
		{
			"event": "training_block",
			"payload": {
				"training_trials": [
					{
						"item": "3_0",
						"word": "wopixu",
						"shape": "3",
						"color": "0"
					},
					{
						"item": "2_2",
						"word": "gafishe",
						"shape": "2",
						"color": "2"
					},
					{
						"item": "1_2",
						"word": "zetishe",
						"shape": "1",
						"color": "2"
					},
					{
						"item": "1_0",
						"word": "zetixu",
						"shape": "1",
						"color": "0"
					}
				],
				"test_trial": {
					"item": "1_0",
					"word": "zetixu",
					"shape": "1",
					"color": "0",
					"catch_trial": false,
					"max_response_time": 20000
				},
				"exposure_time": 2000,
				"pause_time": 500,
				"progress": 0.3467153284671533
			}
		},
		{
			"event": "training_block",
			"payload": {
				"training_trials": [
					{
						"item": "2_0",
						"word": "gafixu",
						"shape": "2",
						"color": "0"
					},
					{
						"item": "1_2",
						"word": "zetishe",
						"shape": "1",
						"color": "2"
					},
					{
						"item": "3_0",
						"word": "wopixu",
						"shape": "3",
						"color": "0"
					},
					{
						"item": "0_0",
						"word": "buvixu",
						"shape": "0",
						"color": "0"
					}
				],
				"test_trial": {
					"item": "3_2",
					"word": "wopishe",
					"shape": "3",
					"color": "2",
					"catch_trial": false,
					"max_response_time": 20000
				},
				"exposure_time": 2000,
				"pause_time": 500,
				"progress": 0.36496350364963503
			}
		},
		{
			"event": "training_block",
			"payload": {
				"training_trials": [
					{
						"item": "2_3",
						"word": "gafitha",
						"shape": "2",
						"color": "3"
					},
					{
						"item": "2_1",
						"word": "gafiso",
						"shape": "2",
						"color": "1"
					},
					{
						"item": "3_2",
						"word": "wopishe",
						"shape": "3",
						"color": "2"
					},
					{
						"item": "1_0",
						"word": "zetixu",
						"shape": "1",
						"color": "0"
					}
				],
				"test_trial": {
					"item": "2_2",
					"word": "gafishe",
					"shape": "2",
					"color": "2",
					"catch_trial": false,
					"max_response_time": 20000
				},
				"exposure_time": 2000,
				"pause_time": 500,
				"progress": 0.38321167883211676
			}
		},
		{
			"event": "training_block",
			"payload": {
				"training_trials": [
					{
						"item": "2_2",
						"word": "gafishe",
						"shape": "2",
						"color": "2"
					},
					{
						"item": "1_1",
						"word": "zetiso",
						"shape": "1",
						"color": "1"
					},
					{
						"item": "3_3",
						"word": "wopitha",
						"shape": "3",
						"color": "3"
					},
					{
						"item": "3_1",
						"word": "wopiso",
						"shape": "3",
						"color": "1"
					}
				],
				"test_trial": {
					"item": "2_0",
					"word": "gafixu",
					"shape": "2",
					"color": "0",
					"catch_trial": false,
					"max_response_time": 20000
				},
				"exposure_time": 2000,
				"pause_time": 500,
				"progress": 0.40145985401459855
			}
		},
		{
			"event": "training_block",
			"payload": {
				"training_trials": [
					{
						"item": "2_2",
						"word": "gafishe",
						"shape": "2",
						"color": "2"
					},
					{
						"item": "3_1",
						"word": "wopiso",
						"shape": "3",
						"color": "1"
					},
					{
						"item": "1_1",
						"word": "zetiso",
						"shape": "1",
						"color": "1"
					},
					{
						"item": "2_1",
						"word": "gafiso",
						"shape": "2",
						"color": "1"
					}
				],
				"test_trial": {
					"item": "2_1",
					"word": "gafiso",
					"shape": "2",
					"color": "1",
					"catch_trial": false,
					"max_response_time": 20000
				},
				"exposure_time": 2000,
				"pause_time": 500,
				"progress": 0.4197080291970803
			}
		},
		{
			"event": "training_block",
			"payload": {
				"training_trials": [
					{
						"item": "2_0",
						"word": "gafixu",
						"shape": "2",
						"color": "0"
					},
					{
						"item": "3_2",
						"word": "wopishe",
						"shape": "3",
						"color": "2"
					},
					{
						"item": "1_0",
						"word": "zetixu",
						"shape": "1",
						"color": "0"
					},
					{
						"item": "1_2",
						"word": "zetishe",
						"shape": "1",
						"color": "2"
					}
				],
				"test_trial": {
					"item": "3_1",
					"word": "wopiso",
					"shape": "3",
					"color": "1",
					"catch_trial": true,
					"max_response_time": 20000
				},
				"exposure_time": 2000,
				"pause_time": 500,
				"progress": 0.43795620437956206
			}
		},
		{
			"event": "training_block",
			"payload": {
				"training_trials": [
					{
						"item": "3_0",
						"word": "wopixu",
						"shape": "3",
						"color": "0"
					},
					{
						"item": "0_0",
						"word": "buvixu",
						"shape": "0",
						"color": "0"
					},
					{
						"item": "2_3",
						"word": "gafitha",
						"shape": "2",
						"color": "3"
					},
					{
						"item": "3_3",
						"word": "wopitha",
						"shape": "3",
						"color": "3"
					}
				],
				"test_trial": {
					"item": "3_3",
					"word": "wopitha",
					"shape": "3",
					"color": "3",
					"catch_trial": false,
					"max_response_time": 20000
				},
				"exposure_time": 2000,
				"pause_time": 500,
				"progress": 0.4562043795620438
			}
		},
		{
			"event": "training_block",
			"payload": {
				"training_trials": [
					{
						"item": "2_0",
						"word": "gafixu",
						"shape": "2",
						"color": "0"
					},
					{
						"item": "1_1",
						"word": "zetiso",
						"shape": "1",
						"color": "1"
					},
					{
						"item": "3_0",
						"word": "wopixu",
						"shape": "3",
						"color": "0"
					},
					{
						"item": "2_3",
						"word": "gafitha",
						"shape": "2",
						"color": "3"
					}
				],
				"test_trial": {
					"item": "2_0",
					"word": "gafixu",
					"shape": "2",
					"color": "0",
					"catch_trial": false,
					"max_response_time": 20000
				},
				"exposure_time": 2000,
				"pause_time": 500,
				"progress": 0.4744525547445255
			}
		},
		{
			"event": "training_block",
			"payload": {
				"training_trials": [
					{
						"item": "2_2",
						"word": "gafishe",
						"shape": "2",
						"color": "2"
					},
					{
						"item": "2_1",
						"word": "gafiso",
						"shape": "2",
						"color": "1"
					},
					{
						"item": "1_2",
						"word": "zetishe",
						"shape": "1",
						"color": "2"
					},
					{
						"item": "3_3",
						"word": "wopitha",
						"shape": "3",
						"color": "3"
					}
				],
				"test_trial": {
					"item": "3_0",
					"word": "wopixu",
					"shape": "3",
					"color": "0",
					"catch_trial": false,
					"max_response_time": 20000
				},
				"exposure_time": 2000,
				"pause_time": 500,
				"progress": 0.4927007299270073
			}
		},
		{
			"event": "training_block",
			"payload": {
				"training_trials": [
					{
						"item": "0_0",
						"word": "buvixu",
						"shape": "0",
						"color": "0"
					},
					{
						"item": "3_1",
						"word": "wopiso",
						"shape": "3",
						"color": "1"
					},
					{
						"item": "3_2",
						"word": "wopishe",
						"shape": "3",
						"color": "2"
					},
					{
						"item": "1_0",
						"word": "zetixu",
						"shape": "1",
						"color": "0"
					}
				],
				"test_trial": {
					"item": "3_2",
					"word": "wopishe",
					"shape": "3",
					"color": "2",
					"catch_trial": false,
					"max_response_time": 20000
				},
				"exposure_time": 2000,
				"pause_time": 500,
				"progress": 0.5109489051094891
			}
		},
		{
			"event": "training_block",
			"payload": {
				"training_trials": [
					{
						"item": "3_3",
						"word": "wopitha",
						"shape": "3",
						"color": "3"
					},
					{
						"item": "3_0",
						"word": "wopixu",
						"shape": "3",
						"color": "0"
					},
					{
						"item": "1_0",
						"word": "zetixu",
						"shape": "1",
						"color": "0"
					},
					{
						"item": "2_0",
						"word": "gafixu",
						"shape": "2",
						"color": "0"
					}
				],
				"test_trial": {
					"item": "1_2",
					"word": "zetishe",
					"shape": "1",
					"color": "2",
					"catch_trial": false,
					"max_response_time": 20000
				},
				"exposure_time": 2000,
				"pause_time": 500,
				"progress": 0.5291970802919708
			}
		},
		{
			"event": "training_block",
			"payload": {
				"training_trials": [
					{
						"item": "2_1",
						"word": "gafiso",
						"shape": "2",
						"color": "1"
					},
					{
						"item": "3_2",
						"word": "wopishe",
						"shape": "3",
						"color": "2"
					},
					{
						"item": "2_2",
						"word": "gafishe",
						"shape": "2",
						"color": "2"
					},
					{
						"item": "2_3",
						"word": "gafitha",
						"shape": "2",
						"color": "3"
					}
				],
				"test_trial": {
					"item": "3_1",
					"word": "wopiso",
					"shape": "3",
					"color": "1",
					"catch_trial": false,
					"max_response_time": 20000
				},
				"exposure_time": 2000,
				"pause_time": 500,
				"progress": 0.5474452554744526
			}
		},
		{
			"event": "training_block",
			"payload": {
				"training_trials": [
					{
						"item": "0_0",
						"word": "buvixu",
						"shape": "0",
						"color": "0"
					},
					{
						"item": "1_2",
						"word": "zetishe",
						"shape": "1",
						"color": "2"
					},
					{
						"item": "3_1",
						"word": "wopiso",
						"shape": "3",
						"color": "1"
					},
					{
						"item": "1_1",
						"word": "zetiso",
						"shape": "1",
						"color": "1"
					}
				],
				"test_trial": {
					"item": "0_0",
					"word": "buvixu",
					"shape": "0",
					"color": "0",
					"catch_trial": false,
					"max_response_time": 20000
				},
				"exposure_time": 2000,
				"pause_time": 500,
				"progress": 0.5656934306569343
			}
		},
		{
			"event": "training_block",
			"payload": {
				"training_trials": [
					{
						"item": "2_2",
						"word": "gafishe",
						"shape": "2",
						"color": "2"
					},
					{
						"item": "2_3",
						"word": "gafitha",
						"shape": "2",
						"color": "3"
					},
					{
						"item": "3_3",
						"word": "wopitha",
						"shape": "3",
						"color": "3"
					},
					{
						"item": "0_0",
						"word": "buvixu",
						"shape": "0",
						"color": "0"
					}
				],
				"test_trial": {
					"item": "2_1",
					"word": "gafiso",
					"shape": "2",
					"color": "1",
					"catch_trial": false,
					"max_response_time": 20000
				},
				"exposure_time": 2000,
				"pause_time": 500,
				"progress": 0.583941605839416
			}
		},
		{
			"event": "training_block",
			"payload": {
				"training_trials": [
					{
						"item": "3_0",
						"word": "wopixu",
						"shape": "3",
						"color": "0"
					},
					{
						"item": "1_0",
						"word": "zetixu",
						"shape": "1",
						"color": "0"
					},
					{
						"item": "3_2",
						"word": "wopishe",
						"shape": "3",
						"color": "2"
					},
					{
						"item": "2_1",
						"word": "gafiso",
						"shape": "2",
						"color": "1"
					}
				],
				"test_trial": {
					"item": "2_3",
					"word": "gafitha",
					"shape": "2",
					"color": "3",
					"catch_trial": false,
					"max_response_time": 20000
				},
				"exposure_time": 2000,
				"pause_time": 500,
				"progress": 0.6021897810218978
			}
		},
		{
			"event": "training_block",
			"payload": {
				"training_trials": [
					{
						"item": "1_1",
						"word": "zetiso",
						"shape": "1",
						"color": "1"
					},
					{
						"item": "3_1",
						"word": "wopiso",
						"shape": "3",
						"color": "1"
					},
					{
						"item": "1_2",
						"word": "zetishe",
						"shape": "1",
						"color": "2"
					},
					{
						"item": "2_0",
						"word": "gafixu",
						"shape": "2",
						"color": "0"
					}
				],
				"test_trial": {
					"item": "2_2",
					"word": "gafishe",
					"shape": "2",
					"color": "2",
					"catch_trial": false,
					"max_response_time": 20000
				},
				"exposure_time": 2000,
				"pause_time": 500,
				"progress": 0.6204379562043796
			}
		},
		{
			"event": "training_block",
			"payload": {
				"training_trials": [
					{
						"item": "3_3",
						"word": "wopitha",
						"shape": "3",
						"color": "3"
					},
					{
						"item": "3_1",
						"word": "wopiso",
						"shape": "3",
						"color": "1"
					},
					{
						"item": "2_1",
						"word": "gafiso",
						"shape": "2",
						"color": "1"
					},
					{
						"item": "1_0",
						"word": "zetixu",
						"shape": "1",
						"color": "0"
					}
				],
				"test_trial": {
					"item": "1_0",
					"word": "zetixu",
					"shape": "1",
					"color": "0",
					"catch_trial": false,
					"max_response_time": 20000
				},
				"exposure_time": 2000,
				"pause_time": 500,
				"progress": 0.6386861313868614
			}
		},
		{
			"event": "training_block",
			"payload": {
				"training_trials": [
					{
						"item": "1_1",
						"word": "zetiso",
						"shape": "1",
						"color": "1"
					},
					{
						"item": "3_2",
						"word": "wopishe",
						"shape": "3",
						"color": "2"
					},
					{
						"item": "2_0",
						"word": "gafixu",
						"shape": "2",
						"color": "0"
					},
					{
						"item": "2_2",
						"word": "gafishe",
						"shape": "2",
						"color": "2"
					}
				],
				"test_trial": {
					"item": "1_1",
					"word": "zetiso",
					"shape": "1",
					"color": "1",
					"catch_trial": true,
					"max_response_time": 20000
				},
				"exposure_time": 2000,
				"pause_time": 500,
				"progress": 0.656934306569343
			}
		},
		{
			"event": "training_block",
			"payload": {
				"training_trials": [
					{
						"item": "0_0",
						"word": "buvixu",
						"shape": "0",
						"color": "0"
					},
					{
						"item": "1_2",
						"word": "zetishe",
						"shape": "1",
						"color": "2"
					},
					{
						"item": "3_0",
						"word": "wopixu",
						"shape": "3",
						"color": "0"
					},
					{
						"item": "2_3",
						"word": "gafitha",
						"shape": "2",
						"color": "3"
					}
				],
				"test_trial": {
					"item": "3_3",
					"word": "wopitha",
					"shape": "3",
					"color": "3",
					"catch_trial": false,
					"max_response_time": 20000
				},
				"exposure_time": 2000,
				"pause_time": 500,
				"progress": 0.6751824817518248
			}
		},
		{
			"event": "instructions",
			"payload": {
				"instruction_screen": "communication",
				"instruction_time": 5000,
				"response_kind": "next_communication",
				"progress": 0.6934306569343066
			}
		},
		{
			"event": "comm_comprehension",
			"payload": {
				"array": [
					"3_2",
					"3_0",
					"2_0",
					"0_3",
					"1_1",
					"3_1",
					"0_0",
					"1_3",
					"2_3",
					"1_0",
					"3_3",
					"2_1",
					"2_2",
					"0_1",
					"0_2",
					"1_2"
				],
				"pause_time": 500,
				"progress": 0.7299270072992701
			}
		},
		{
			"event": "comm_production",
			"payload": {
				"item": "3_1",
				"word": "wopiso",
				"shape": "3",
				"color": "1",
				"pause_time": 500,
				"progress": 0.7372262773722628
			}
		},
		{
			"event": "comm_comprehension",
			"payload": {
				"array": [
					"3_3",
					"1_1",
					"0_3",
					"1_2",
					"0_1",
					"2_1",
					"2_2",
					"3_2",
					"2_0",
					"3_0",
					"2_3",
					"1_3",
					"0_0",
					"1_0",
					"3_1",
					"0_2"
				],
				"pause_time": 500,
				"progress": 0.7445255474452555
			}
		},
		{
			"event": "comm_production",
			"payload": {
				"item": "1_0",
				"word": "zetixu",
				"shape": "1",
				"color": "0",
				"pause_time": 500,
				"progress": 0.7518248175182481
			}
		},
		{
			"event": "comm_comprehension",
			"payload": {
				"array": [
					"2_2",
					"3_1",
					"1_0",
					"0_1",
					"0_2",
					"2_3",
					"3_2",
					"1_3",
					"0_3",
					"3_0",
					"3_3",
					"2_1",
					"1_1",
					"0_0",
					"2_0",
					"1_2"
				],
				"pause_time": 500,
				"progress": 0.7591240875912408
			}
		},
		{
			"event": "comm_production",
			"payload": {
				"item": "1_1",
				"word": "zetiso",
				"shape": "1",
				"color": "1",
				"pause_time": 500,
				"progress": 0.7664233576642335
			}
		},
		{
			"event": "comm_comprehension",
			"payload": {
				"array": [
					"1_3",
					"0_0",
					"0_2",
					"1_2",
					"1_1",
					"0_1",
					"3_2",
					"0_3",
					"2_3",
					"3_0",
					"3_1",
					"2_0",
					"2_2",
					"2_1",
					"1_0",
					"3_3"
				],
				"pause_time": 500,
				"progress": 0.7737226277372263
			}
		},
		{
			"event": "comm_production",
			"payload": {
				"item": "0_1",
				"word": "buviso",
				"shape": "0",
				"color": "1",
				"pause_time": 500,
				"progress": 0.781021897810219
			}
		},
		{
			"event": "comm_comprehension",
			"payload": {
				"array": [
					"0_3",
					"1_2",
					"3_0",
					"1_1",
					"2_2",
					"1_0",
					"3_3",
					"2_3",
					"0_2",
					"2_1",
					"3_1",
					"0_0",
					"3_2",
					"1_3",
					"2_0",
					"0_1"
				],
				"pause_time": 500,
				"progress": 0.7883211678832117
			}
		},
		{
			"event": "comm_production",
			"payload": {
				"item": "0_0",
				"word": "buvixu",
				"shape": "0",
				"color": "0",
				"pause_time": 500,
				"progress": 0.7956204379562044
			}
		},
		{
			"event": "comm_comprehension",
			"payload": {
				"array": [
					"2_3",
					"3_1",
					"1_3",
					"0_0",
					"3_2",
					"0_1",
					"1_1",
					"3_3",
					"1_2",
					"0_3",
					"3_0",
					"1_0",
					"0_2",
					"2_2",
					"2_0",
					"2_1"
				],
				"pause_time": 500,
				"progress": 0.8029197080291971
			}
		},
		{
			"event": "comm_production",
			"payload": {
				"item": "2_2",
				"word": "gafishe",
				"shape": "2",
				"color": "2",
				"pause_time": 500,
				"progress": 0.8102189781021898
			}
		},
		{
			"event": "comm_comprehension",
			"payload": {
				"array": [
					"1_0",
					"1_3",
					"3_3",
					"3_2",
					"0_0",
					"2_3",
					"0_3",
					"1_2",
					"2_1",
					"3_1",
					"3_0",
					"2_0",
					"2_2",
					"0_2",
					"0_1",
					"1_1"
				],
				"pause_time": 500,
				"progress": 0.8175182481751825
			}
		},
		{
			"event": "comm_production",
			"payload": {
				"item": "3_0",
				"word": "wopixu",
				"shape": "3",
				"color": "0",
				"pause_time": 500,
				"progress": 0.8248175182481752
			}
		},
		{
			"event": "comm_comprehension",
			"payload": {
				"array": [
					"0_2",
					"2_3",
					"3_3",
					"2_0",
					"2_1",
					"2_2",
					"0_1",
					"3_0",
					"3_1",
					"1_1",
					"1_2",
					"0_3",
					"1_0",
					"1_3",
					"3_2",
					"0_0"
				],
				"pause_time": 500,
				"progress": 0.8321167883211679
			}
		},
		{
			"event": "comm_production",
			"payload": {
				"item": "0_2",
				"word": "buvishe",
				"shape": "0",
				"color": "2",
				"pause_time": 500,
				"progress": 0.8394160583941606
			}
		},
		{
			"event": "comm_comprehension",
			"payload": {
				"array": [
					"3_2",
					"2_3",
					"2_2",
					"1_1",
					"1_3",
					"2_0",
					"3_3",
					"0_3",
					"0_1",
					"0_2",
					"3_0",
					"0_0",
					"1_2",
					"3_1",
					"1_0",
					"2_1"
				],
				"pause_time": 500,
				"progress": 0.8467153284671532
			}
		},
		{
			"event": "comm_production",
			"payload": {
				"item": "1_3",
				"word": "zetitha",
				"shape": "1",
				"color": "3",
				"pause_time": 500,
				"progress": 0.8540145985401459
			}
		},
		{
			"event": "comm_comprehension",
			"payload": {
				"array": [
					"3_2",
					"3_3",
					"3_1",
					"0_0",
					"1_0",
					"0_1",
					"1_2",
					"1_1",
					"3_0",
					"1_3",
					"2_3",
					"0_3",
					"2_0",
					"2_1",
					"0_2",
					"2_2"
				],
				"pause_time": 500,
				"progress": 0.8613138686131386
			}
		},
		{
			"event": "comm_production",
			"payload": {
				"item": "3_2",
				"word": "wopishe",
				"shape": "3",
				"color": "2",
				"pause_time": 500,
				"progress": 0.8686131386861314
			}
		},
		{
			"event": "comm_comprehension",
			"payload": {
				"array": [
					"1_2",
					"0_2",
					"0_3",
					"3_1",
					"2_3",
					"0_1",
					"3_2",
					"1_1",
					"1_0",
					"3_0",
					"1_3",
					"3_3",
					"0_0",
					"2_0",
					"2_2",
					"2_1"
				],
				"pause_time": 500,
				"progress": 0.8759124087591241
			}
		},
		{
			"event": "comm_production",
			"payload": {
				"item": "2_1",
				"word": "gafiso",
				"shape": "2",
				"color": "1",
				"pause_time": 500,
				"progress": 0.8832116788321168
			}
		},
		{
			"event": "comm_comprehension",
			"payload": {
				"array": [
					"3_3",
					"3_2",
					"2_2",
					"3_1",
					"1_1",
					"3_0",
					"1_0",
					"0_2",
					"0_0",
					"1_2",
					"1_3",
					"2_0",
					"2_1",
					"0_1",
					"0_3",
					"2_3"
				],
				"pause_time": 500,
				"progress": 0.8905109489051095
			}
		},
		{
			"event": "comm_production",
			"payload": {
				"item": "3_3",
				"word": "wopitha",
				"shape": "3",
				"color": "3",
				"pause_time": 500,
				"progress": 0.8978102189781022
			}
		},
		{
			"event": "comm_comprehension",
			"payload": {
				"array": [
					"1_1",
					"2_3",
					"1_3",
					"0_0",
					"1_0",
					"0_2",
					"1_2",
					"0_1",
					"3_3",
					"3_1",
					"3_0",
					"2_2",
					"2_0",
					"2_1",
					"3_2",
					"0_3"
				],
				"pause_time": 500,
				"progress": 0.9051094890510949
			}
		},
		{
			"event": "comm_production",
			"payload": {
				"item": "2_3",
				"word": "gafitha",
				"shape": "2",
				"color": "3",
				"pause_time": 500,
				"progress": 0.9124087591240876
			}
		},
		{
			"event": "comm_comprehension",
			"payload": {
				"array": [
					"2_3",
					"0_3",
					"0_0",
					"2_0",
					"2_1",
					"3_1",
					"2_2",
					"0_1",
					"3_0",
					"3_2",
					"0_2",
					"1_2",
					"1_0",
					"1_1",
					"3_3",
					"1_3"
				],
				"pause_time": 500,
				"progress": 0.9197080291970803
			}
		},
		{
			"event": "comm_production",
			"payload": {
				"item": "1_2",
				"word": "zetishe",
				"shape": "1",
				"color": "2",
				"pause_time": 500,
				"progress": 0.927007299270073
			}
		},
		{
			"event": "comm_comprehension",
			"payload": {
				"array": [
					"2_1",
					"2_2",
					"1_1",
					"2_0",
					"1_3",
					"1_2",
					"2_3",
					"0_2",
					"3_2",
					"0_0",
					"1_0",
					"3_1",
					"3_0",
					"0_1",
					"3_3",
					"0_3"
				],
				"pause_time": 500,
				"progress": 0.9343065693430657
			}
		},
		{
			"event": "comm_production",
			"payload": {
				"item": "0_3",
				"word": "buvitha",
				"shape": "0",
				"color": "3",
				"pause_time": 500,
				"progress": 0.9416058394160584
			}
		},
		{
			"event": "comm_comprehension",
			"payload": {
				"array": [
					"2_2",
					"2_3",
					"1_0",
					"3_2",
					"2_0",
					"3_3",
					"3_0",
					"3_1",
					"1_1",
					"0_2",
					"0_0",
					"1_3",
					"2_1",
					"1_2",
					"0_1",
					"0_3"
				],
				"pause_time": 500,
				"progress": 0.948905109489051
			}
		},
		{
			"event": "comm_production",
			"payload": {
				"item": "2_0",
				"word": "gafixu",
				"shape": "2",
				"color": "0",
				"pause_time": 500,
				"progress": 0.9562043795620438
			}
		},
		{
			"event": "questionnaire",
			"payload": {
				"progress": 0.9635036496350365
			}
		},
		{
			"event": "end_of_experiment",
			"payload": {
				"return_url": "https://app.prolific.co/submissions/complete?cc=CIYLN87N",
				"basic_pay": 300,
				"progress": 1
			}
		}
	],
	"n_reinitializations": 0,
	"sequence_position": 73,
	"total_bonus": 40,
	"responses": [
		{
			"test_type": "mini_test",
			"shape": "1",
			"color": "0",
			"expected_label": "zetixu",
			"catch_trial": false,
			"input_label": "zetiso",
			"response_time": 2416,
			"object_clicked": false,
			"time": 1687864754
		},
		{
			"test_type": "mini_test",
			"shape": "0",
			"color": "0",
			"expected_label": "buvixu",
			"catch_trial": false,
			"input_label": "wotishe",
			"response_time": 4327,
			"object_clicked": false,
			"time": 1687864768
		},
		{
			"test_type": "mini_test",
			"shape": "2",
			"color": "3",
			"expected_label": "gafitha",
			"catch_trial": false,
			"input_label": "gafita",
			"response_time": 3820,
			"object_clicked": false,
			"time": 1687864782
		},
		{
			"test_type": "mini_test",
			"shape": "1",
			"color": "2",
			"expected_label": "zetishe",
			"catch_trial": false,
			"input_label": "zetishe",
			"response_time": 2361,
			"object_clicked": false,
			"time": 1687864794
		},
		{
			"test_type": "mini_test",
			"shape": "2",
			"color": "1",
			"expected_label": "gafiso",
			"catch_trial": false,
			"input_label": "gafishe",
			"response_time": 2508,
			"object_clicked": false,
			"time": 1687864806
		},
		{
			"test_type": "mini_test",
			"shape": "3",
			"color": "2",
			"expected_label": "wopishe",
			"catch_trial": false,
			"input_label": "wopitha",
			"response_time": 2394,
			"object_clicked": false,
			"time": 1687864818
		},
		{
			"test_type": "mini_test",
			"shape": "3",
			"color": "3",
			"expected_label": "wopitha",
			"catch_trial": false,
			"input_label": "wophita",
			"response_time": 3705,
			"object_clicked": false,
			"time": 1687864831
		},
		{
			"test_type": "mini_test",
			"shape": "1",
			"color": "1",
			"expected_label": "zetiso",
			"catch_trial": false,
			"input_label": "zetishe",
			"response_time": 4430,
			"object_clicked": false,
			"time": 1687864845
		},
		{
			"test_type": "mini_test",
			"shape": "2",
			"color": "0",
			"expected_label": "gafixu",
			"catch_trial": false,
			"input_label": "gaftha",
			"response_time": 6530,
			"object_clicked": false,
			"time": 1687864861
		},
		{
			"test_type": "mini_test",
			"shape": "2",
			"color": "2",
			"expected_label": "gafishe",
			"catch_trial": false,
			"input_label": "whopitha",
			"response_time": 7535,
			"object_clicked": false,
			"time": 1687864878
		},
		{
			"test_type": "mini_test",
			"shape": "3",
			"color": "0",
			"expected_label": "wopixu",
			"catch_trial": true,
			"input_label": "wophixu",
			"response_time": 10894,
			"object_clicked": true,
			"time": 1687864899
		},
		{
			"test_type": "mini_test",
			"shape": "3",
			"color": "1",
			"expected_label": "wopiso",
			"catch_trial": false,
			"input_label": "wophixu",
			"response_time": 3684,
			"object_clicked": false,
			"time": 1687864912
		},
		{
			"test_type": "mini_test",
			"shape": "1",
			"color": "2",
			"expected_label": "zetishe",
			"catch_trial": false,
			"input_label": "gafishe",
			"response_time": 3541,
			"object_clicked": false,
			"time": 1687864925
		},
		{
			"test_type": "mini_test",
			"shape": "1",
			"color": "1",
			"expected_label": "zetiso",
			"catch_trial": false,
			"input_label": "zethishe",
			"response_time": 5207,
			"object_clicked": false,
			"time": 1687864940
		},
		{
			"test_type": "mini_test",
			"shape": "3",
			"color": "0",
			"expected_label": "wopixu",
			"catch_trial": false,
			"input_label": "whopitha",
			"response_time": 4501,
			"object_clicked": false,
			"time": 1687864954
		},
		{
			"test_type": "mini_test",
			"shape": "2",
			"color": "3",
			"expected_label": "gafitha",
			"catch_trial": false,
			"input_label": "gafitha",
			"response_time": 2408,
			"object_clicked": false,
			"time": 1687864966
		},
		{
			"test_type": "mini_test",
			"shape": "0",
			"color": "0",
			"expected_label": "buvixu",
			"catch_trial": false,
			"input_label": "buvixu",
			"response_time": 3669,
			"object_clicked": false,
			"time": 1687864979
		},
		{
			"test_type": "mini_test",
			"shape": "1",
			"color": "0",
			"expected_label": "zetixu",
			"catch_trial": false,
			"input_label": "zetixu",
			"response_time": 3548,
			"object_clicked": false,
			"time": 1687864992
		},
		{
			"test_type": "mini_test",
			"shape": "3",
			"color": "2",
			"expected_label": "wopishe",
			"catch_trial": false,
			"input_label": "wophishe",
			"response_time": 7509,
			"object_clicked": false,
			"time": 1687865010
		},
		{
			"test_type": "mini_test",
			"shape": "2",
			"color": "2",
			"expected_label": "gafishe",
			"catch_trial": false,
			"input_label": "wopishe",
			"response_time": 7695,
			"object_clicked": false,
			"time": 1687865027
		},
		{
			"test_type": "mini_test",
			"shape": "2",
			"color": "0",
			"expected_label": "gafixu",
			"catch_trial": false,
			"input_label": "gafitha",
			"response_time": 5321,
			"object_clicked": false,
			"time": 1687865042
		},
		{
			"test_type": "mini_test",
			"shape": "2",
			"color": "1",
			"expected_label": "gafiso",
			"catch_trial": false,
			"input_label": "gafiso",
			"response_time": 2163,
			"object_clicked": false,
			"time": 1687865054
		},
		{
			"test_type": "mini_test",
			"shape": "3",
			"color": "1",
			"expected_label": "wopiso",
			"catch_trial": true,
			"input_label": "wopihxu",
			"response_time": 10727,
			"object_clicked": true,
			"time": 1687865074
		},
		{
			"test_type": "mini_test",
			"shape": "3",
			"color": "3",
			"expected_label": "wopitha",
			"catch_trial": false,
			"input_label": "wophita",
			"response_time": 3502,
			"object_clicked": false,
			"time": 1687865087
		},
		{
			"test_type": "mini_test",
			"shape": "2",
			"color": "0",
			"expected_label": "gafixu",
			"catch_trial": false,
			"input_label": "gafixu",
			"response_time": 5973,
			"object_clicked": false,
			"time": 1687865103
		},
		{
			"test_type": "mini_test",
			"shape": "3",
			"color": "0",
			"expected_label": "wopixu",
			"catch_trial": false,
			"input_label": "wophixu",
			"response_time": 3531,
			"object_clicked": false,
			"time": 1687865116
		},
		{
			"test_type": "mini_test",
			"shape": "3",
			"color": "2",
			"expected_label": "wopishe",
			"catch_trial": false,
			"input_label": "wophitha",
			"response_time": 5211,
			"object_clicked": false,
			"time": 1687865130
		},
		{
			"test_type": "mini_test",
			"shape": "1",
			"color": "2",
			"expected_label": "zetishe",
			"catch_trial": false,
			"input_label": "wophita",
			"response_time": 3079,
			"object_clicked": false,
			"time": 1687865143
		},
		{
			"test_type": "mini_test",
			"shape": "3",
			"color": "1",
			"expected_label": "wopiso",
			"catch_trial": false,
			"input_label": "wophishe",
			"response_time": 5042,
			"object_clicked": false,
			"time": 1687865158
		},
		{
			"test_type": "mini_test",
			"shape": "0",
			"color": "0",
			"expected_label": "buvixu",
			"catch_trial": false,
			"input_label": "buvixu",
			"response_time": 6222,
			"object_clicked": false,
			"time": 1687865174
		},
		{
			"test_type": "mini_test",
			"shape": "2",
			"color": "1",
			"expected_label": "gafiso",
			"catch_trial": false,
			"input_label": "zetishe",
			"response_time": 7820,
			"object_clicked": false,
			"time": 1687865191
		},
		{
			"test_type": "mini_test",
			"shape": "2",
			"color": "3",
			"expected_label": "gafitha",
			"catch_trial": false,
			"input_label": "gafitha",
			"response_time": 4936,
			"object_clicked": false,
			"time": 1687865206
		},
		{
			"test_type": "mini_test",
			"shape": "2",
			"color": "2",
			"expected_label": "gafishe",
			"catch_trial": false,
			"input_label": "gafishe",
			"response_time": 5670,
			"object_clicked": false,
			"time": 1687865221
		},
		{
			"test_type": "mini_test",
			"shape": "1",
			"color": "0",
			"expected_label": "zetixu",
			"catch_trial": false,
			"input_label": "zethixu",
			"response_time": 8445,
			"object_clicked": false,
			"time": 1687865239
		},
		{
			"test_type": "mini_test",
			"shape": "1",
			"color": "1",
			"expected_label": "zetiso",
			"catch_trial": true,
			"input_label": "gafishe",
			"response_time": 8908,
			"object_clicked": true,
			"time": 1687865257
		},
		{
			"test_type": "mini_test",
			"shape": "3",
			"color": "3",
			"expected_label": "wopitha",
			"catch_trial": false,
			"input_label": "gafitha",
			"response_time": 2219,
			"object_clicked": false,
			"time": 1687865269
		},
		{
			"test_type": "comm_comprehension",
			"item": "1_1",
			"word": "zetixo",
			"selected_button": 11,
			"selected_item": "2_1",
			"response_time": 11706,
			"time": 1687865392
		},
		{
			"test_type": "comm_production",
			"shape": "3",
			"color": "1",
			"item": "3_1",
			"expected_label": "wopiso",
			"input_label": "wopiso",
			"response_time": 21818,
			"time": 1687865415
		},
		{
			"test_type": "comm_comprehension",
			"item": "0_2",
			"word": "buvishe",
			"selected_button": 15,
			"selected_item": "0_2",
			"response_time": 2845,
			"time": 1687865448
		},
		{
			"test_type": "comm_production",
			"shape": "1",
			"color": "0",
			"item": "1_0",
			"expected_label": "zetixu",
			"input_label": "zetixu",
			"response_time": 3228,
			"time": 1687865453
		},
		{
			"test_type": "comm_comprehension",
			"item": "1_3",
			"word": "zetitha",
			"selected_button": 11,
			"selected_item": "2_1",
			"response_time": 4921,
			"time": 1687865477
		},
		{
			"test_type": "comm_production",
			"shape": "1",
			"color": "1",
			"item": "1_1",
			"expected_label": "zetiso",
			"input_label": "zetiso",
			"response_time": 2409,
			"time": 1687865481
		},
		{
			"test_type": "comm_comprehension",
			"item": "0_1",
			"word": "buviso",
			"selected_button": 1,
			"selected_item": "0_0",
			"response_time": 5626,
			"time": 1687865538
		},
		{
			"test_type": "comm_production",
			"shape": "0",
			"color": "1",
			"item": "0_1",
			"expected_label": "buviso",
			"input_label": "buviso",
			"response_time": 2170,
			"time": 1687865541
		},
		{
			"test_type": "comm_comprehension",
			"item": "3_3",
			"word": "wopitha",
			"selected_button": 12,
			"selected_item": "3_2",
			"response_time": 3464,
			"time": 1687865553
		},
		{
			"test_type": "comm_production",
			"shape": "0",
			"color": "0",
			"item": "0_0",
			"expected_label": "buvixu",
			"input_label": "buvixu",
			"response_time": 3083,
			"time": 1687865558
		},
		{
			"test_type": "comm_comprehension",
			"item": "3_1",
			"word": "wopisho",
			"selected_button": 4,
			"selected_item": "3_2",
			"response_time": 6314,
			"time": 1687865599
		},
		{
			"test_type": "comm_production",
			"shape": "2",
			"color": "2",
			"item": "2_2",
			"expected_label": "gafishe",
			"input_label": "gafishe",
			"response_time": 2675,
			"time": 1687865603
		},
		{
			"test_type": "comm_comprehension",
			"item": "2_0",
			"word": "gafixu",
			"selected_button": 15,
			"selected_item": "1_1",
			"response_time": 3608,
			"time": 1687865625
		},
		{
			"test_type": "comm_production",
			"shape": "3",
			"color": "0",
			"item": "3_0",
			"expected_label": "wopixu",
			"input_label": "wopixu",
			"response_time": 7336,
			"time": 1687865634
		},
		{
			"test_type": "comm_comprehension",
			"item": "3_2",
			"word": "wopishe",
			"selected_button": 6,
			"selected_item": "0_1",
			"response_time": 9050,
			"time": 1687865661
		},
		{
			"test_type": "comm_production",
			"shape": "0",
			"color": "2",
			"item": "0_2",
			"expected_label": "buvishe",
			"input_label": "buvishe",
			"response_time": 2136,
			"time": 1687865665
		},
		{
			"test_type": "comm_comprehension",
			"item": "1_2",
			"word": "zetishe",
			"selected_button": 5,
			"selected_item": "2_0",
			"response_time": 5553,
			"time": 1687865687
		},
		{
			"test_type": "comm_production",
			"shape": "1",
			"color": "3",
			"item": "1_3",
			"expected_label": "zetitha",
			"input_label": "zetitha",
			"response_time": 11082,
			"time": 1687865699
		},
		{
			"test_type": "comm_comprehension",
			"item": "0_0",
			"word": "buvivu",
			"selected_button": 14,
			"selected_item": "0_2",
			"response_time": 4817,
			"time": 1687865953
		},
		{
			"test_type": "comm_production",
			"shape": "3",
			"color": "2",
			"item": "3_2",
			"expected_label": "wopishe",
			"input_label": "wopishe",
			"response_time": 4575,
			"time": 1687865959
		},
		{
			"test_type": "comm_comprehension",
			"item": "2_1",
			"word": "gafiso",
			"selected_button": 8,
			"selected_item": "1_0",
			"response_time": 3154,
			"time": 1687865970
		},
		{
			"test_type": "comm_production",
			"shape": "2",
			"color": "1",
			"item": "2_1",
			"expected_label": "gafiso",
			"input_label": "gafiso",
			"response_time": 2103,
			"time": 1687865974
		},
		{
			"test_type": "comm_comprehension",
			"item": "0_3",
			"word": "buvitha",
			"selected_button": 9,
			"selected_item": "1_2",
			"response_time": 3719,
			"time": 1687865986
		},
		{
			"test_type": "comm_production",
			"shape": "3",
			"color": "3",
			"item": "3_3",
			"expected_label": "wopitha",
			"input_label": "wopitha",
			"response_time": 3488,
			"time": 1687865991
		},
		{
			"test_type": "comm_comprehension",
			"item": "1_0",
			"word": "zetixu",
			"selected_button": 6,
			"selected_item": "1_2",
			"response_time": 7399,
			"time": 1687866030
		},
		{
			"test_type": "comm_production",
			"shape": "2",
			"color": "3",
			"item": "2_3",
			"expected_label": "gafitha",
			"input_label": "gafitha",
			"response_time": 3206,
			"time": 1687866034
		},
		{
			"test_type": "comm_comprehension",
			"item": "2_3",
			"word": "gafitha",
			"selected_button": 1,
			"selected_item": "0_3",
			"response_time": 5333,
			"time": 1687866125
		},
		{
			"test_type": "comm_production",
			"shape": "1",
			"color": "2",
			"item": "1_2",
			"expected_label": "zetishe",
			"input_label": "zetishe",
			"response_time": 4404,
			"time": 1687866131
		},
		{
			"test_type": "comm_comprehension",
			"item": "2_2",
			"word": "gafixe",
			"selected_button": 0,
			"selected_item": "2_1",
			"response_time": 4016,
			"time": 1687866149
		},
		{
			"test_type": "comm_production",
			"shape": "0",
			"color": "3",
			"item": "0_3",
			"expected_label": "buvitha",
			"input_label": "buvitha",
			"response_time": 5357,
			"time": 1687866156
		},
		{
			"test_type": "comm_comprehension",
			"item": "3_0",
			"word": "wopixu",
			"selected_button": 13,
			"selected_item": "1_2",
			"response_time": 5324,
			"time": 1687866174
		},
		{
			"test_type": "comm_production",
			"shape": "2",
			"color": "0",
			"item": "2_0",
			"expected_label": "gafixu",
			"input_label": "gafitha",
			"response_time": 3447,
			"time": 1687866179
		}
	],
	"comments": "I noticed patterns among similar shapes and colours. I did not use notes.",
	"lexicon": {
		"0_0": "buvixu",
		"0_1": "buviso",
		"0_2": "buvishe",
		"0_3": "buvitha",
		"1_0": "zetixu",
		"1_1": "zetiso",
		"1_2": "zetishe",
		"1_3": "zetitha",
		"2_0": "gafitha",
		"2_1": "gafiso",
		"2_2": "gafishe",
		"2_3": "gafitha",
		"3_0": "wopixu",
		"3_1": "wopiso",
		"3_2": "wopishe",
		"3_3": "wopitha"
	}
}