{
	"subject_id": "044",
	"client_id": null,
	"creation_time": 1683212983,
	"modified_time": 1683213881,
	"status": "approved",
	"chain_id": "lrn_hiVar_5",
	"generation": 2,
	"input_lexicon": {
		"0_0": "buvecow",
		"0_1": "buvikow",
		"0_2": "buvykow",
		"0_3": "buvyckow",
		"1_0": "zetickoe",
		"1_1": "zeteecoe",
		"1_2": "zeteekow",
		"1_3": "zeteeckoh",
		"2_0": "gafeecow",
		"2_1": "gafeecoh",
		"2_2": "gafykoe",
		"2_3": "gafeeckoh",
		"3_0": "wopickoe",
		"3_1": "wopeeckoe",
		"3_2": "wopyckoe",
		"3_3": "wopikoh"
	},
	"training_items": [
		"1_3",
		"2_0",
		"2_1",
		"0_3",
		"0_1",
		"2_2",
		"1_0",
		"0_2",
		"3_1",
		"1_2",
		"3_3",
		"1_1"
	],
	"trial_sequence": [
		{
			"event": "consent",
			"payload": {
				"progress": 0
			}
		},
		{
			"event": "instructions",
			"payload": {
				"instruction_screen": "training",
				"instruction_time": 5000,
				"response_kind": "ready_to_assign",
				"progress": 0
			}
		},
		{
			"event": "instructions",
			"payload": {
				"instruction_screen": "training_for_test",
				"instruction_time": 5000,
				"response_kind": "next",
				"progress": 0
			}
		},
		{
			"event": "training_block",
			"payload": {
				"training_trials": [
					{
						"item": "2_2",
						"word": "gafykoe",
						"shape": "2",
						"color": "2"
					},
					{
						"item": "1_2",
						"word": "zeteekow",
						"shape": "1",
						"color": "2"
					},
					{
						"item": "0_3",
						"word": "buvyckow",
						"shape": "0",
						"color": "3"
					},
					{
						"item": "3_3",
						"word": "wopikoh",
						"shape": "3",
						"color": "3"
					}
				],
				"test_trial": {
					"item": "3_3",
					"word": "wopikoh",
					"shape": "3",
					"color": "3",
					"catch_trial": false,
					"max_response_time": 20000
				},
				"exposure_time": 2000,
				"pause_time": 500,
				"progress": 0.0364963503649635
			}
		},
		{
			"event": "training_block",
			"payload": {
				"training_trials": [
					{
						"item": "0_1",
						"word": "buvikow",
						"shape": "0",
						"color": "1"
					},
					{
						"item": "1_3",
						"word": "zeteeckoh",
						"shape": "1",
						"color": "3"
					},
					{
						"item": "3_1",
						"word": "wopeeckoe",
						"shape": "3",
						"color": "1"
					},
					{
						"item": "1_0",
						"word": "zetickoe",
						"shape": "1",
						"color": "0"
					}
				],
				"test_trial": {
					"item": "2_2",
					"word": "gafykoe",
					"shape": "2",
					"color": "2",
					"catch_trial": false,
					"max_response_time": 20000
				},
				"exposure_time": 2000,
				"pause_time": 500,
				"progress": 0.05474452554744526
			}
		},
		{
			"event": "training_block",
			"payload": {
				"training_trials": [
					{
						"item": "2_0",
						"word": "gafeecow",
						"shape": "2",
						"color": "0"
					},
					{
						"item": "0_2",
						"word": "buvykow",
						"shape": "0",
						"color": "2"
					},
					{
						"item": "2_1",
						"word": "gafeecoh",
						"shape": "2",
						"color": "1"
					},
					{
						"item": "1_1",
						"word": "zeteecoe",
						"shape": "1",
						"color": "1"
					}
				],
				"test_trial": {
					"item": "0_2",
					"word": "buvykow",
					"shape": "0",
					"color": "2",
					"catch_trial": false,
					"max_response_time": 20000
				},
				"exposure_time": 2000,
				"pause_time": 500,
				"progress": 0.072992700729927
			}
		},
		{
			"event": "training_block",
			"payload": {
				"training_trials": [
					{
						"item": "0_1",
						"word": "buvikow",
						"shape": "0",
						"color": "1"
					},
					{
						"item": "2_2",
						"word": "gafykoe",
						"shape": "2",
						"color": "2"
					},
					{
						"item": "2_1",
						"word": "gafeecoh",
						"shape": "2",
						"color": "1"
					},
					{
						"item": "1_1",
						"word": "zeteecoe",
						"shape": "1",
						"color": "1"
					}
				],
				"test_trial": {
					"item": "1_3",
					"word": "zeteeckoh",
					"shape": "1",
					"color": "3",
					"catch_trial": false,
					"max_response_time": 20000
				},
				"exposure_time": 2000,
				"pause_time": 500,
				"progress": 0.09124087591240876
			}
		},
		{
			"event": "training_block",
			"payload": {
				"training_trials": [
					{
						"item": "3_3",
						"word": "wopikoh",
						"shape": "3",
						"color": "3"
					},
					{
						"item": "2_0",
						"word": "gafeecow",
						"shape": "2",
						"color": "0"
					},
					{
						"item": "1_0",
						"word": "zetickoe",
						"shape": "1",
						"color": "0"
					},
					{
						"item": "1_2",
						"word": "zeteekow",
						"shape": "1",
						"color": "2"
					}
				],
				"test_trial": {
					"item": "0_3",
					"word": "buvyckow",
					"shape": "0",
					"color": "3",
					"catch_trial": false,
					"max_response_time": 20000
				},
				"exposure_time": 2000,
				"pause_time": 500,
				"progress": 0.10948905109489052
			}
		},
		{
			"event": "training_block",
			"payload": {
				"training_trials": [
					{
						"item": "1_3",
						"word": "zeteeckoh",
						"shape": "1",
						"color": "3"
					},
					{
						"item": "0_3",
						"word": "buvyckow",
						"shape": "0",
						"color": "3"
					},
					{
						"item": "3_1",
						"word": "wopeeckoe",
						"shape": "3",
						"color": "1"
					},
					{
						"item": "0_2",
						"word": "buvykow",
						"shape": "0",
						"color": "2"
					}
				],
				"test_trial": {
					"item": "3_1",
					"word": "wopeeckoe",
					"shape": "3",
					"color": "1",
					"catch_trial": false,
					"max_response_time": 20000
				},
				"exposure_time": 2000,
				"pause_time": 500,
				"progress": 0.12773722627737227
			}
		},
		{
			"event": "training_block",
			"payload": {
				"training_trials": [
					{
						"item": "0_3",
						"word": "buvyckow",
						"shape": "0",
						"color": "3"
					},
					{
						"item": "1_1",
						"word": "zeteecoe",
						"shape": "1",
						"color": "1"
					},
					{
						"item": "2_1",
						"word": "gafeecoh",
						"shape": "2",
						"color": "1"
					},
					{
						"item": "2_2",
						"word": "gafykoe",
						"shape": "2",
						"color": "2"
					}
				],
				"test_trial": {
					"item": "2_0",
					"word": "gafeecow",
					"shape": "2",
					"color": "0",
					"catch_trial": false,
					"max_response_time": 20000
				},
				"exposure_time": 2000,
				"pause_time": 500,
				"progress": 0.145985401459854
			}
		},
		{
			"event": "training_block",
			"payload": {
				"training_trials": [
					{
						"item": "0_1",
						"word": "buvikow",
						"shape": "0",
						"color": "1"
					},
					{
						"item": "1_2",
						"word": "zeteekow",
						"shape": "1",
						"color": "2"
					},
					{
						"item": "1_0",
						"word": "zetickoe",
						"shape": "1",
						"color": "0"
					},
					{
						"item": "3_3",
						"word": "wopikoh",
						"shape": "3",
						"color": "3"
					}
				],
				"test_trial": {
					"item": "1_2",
					"word": "zeteekow",
					"shape": "1",
					"color": "2",
					"catch_trial": false,
					"max_response_time": 20000
				},
				"exposure_time": 2000,
				"pause_time": 500,
				"progress": 0.16423357664233576
			}
		},
		{
			"event": "training_block",
			"payload": {
				"training_trials": [
					{
						"item": "1_3",
						"word": "zeteeckoh",
						"shape": "1",
						"color": "3"
					},
					{
						"item": "2_0",
						"word": "gafeecow",
						"shape": "2",
						"color": "0"
					},
					{
						"item": "0_2",
						"word": "buvykow",
						"shape": "0",
						"color": "2"
					},
					{
						"item": "3_1",
						"word": "wopeeckoe",
						"shape": "3",
						"color": "1"
					}
				],
				"test_trial": {
					"item": "2_1",
					"word": "gafeecoh",
					"shape": "2",
					"color": "1",
					"catch_trial": false,
					"max_response_time": 20000
				},
				"exposure_time": 2000,
				"pause_time": 500,
				"progress": 0.18248175182481752
			}
		},
		{
			"event": "training_block",
			"payload": {
				"training_trials": [
					{
						"item": "1_0",
						"word": "zetickoe",
						"shape": "1",
						"color": "0"
					},
					{
						"item": "2_1",
						"word": "gafeecoh",
						"shape": "2",
						"color": "1"
					},
					{
						"item": "3_3",
						"word": "wopikoh",
						"shape": "3",
						"color": "3"
					},
					{
						"item": "0_1",
						"word": "buvikow",
						"shape": "0",
						"color": "1"
					}
				],
				"test_trial": {
					"item": "1_1",
					"word": "zeteecoe",
					"shape": "1",
					"color": "1",
					"catch_trial": false,
					"max_response_time": 20000
				},
				"exposure_time": 2000,
				"pause_time": 500,
				"progress": 0.20072992700729927
			}
		},
		{
			"event": "training_block",
			"payload": {
				"training_trials": [
					{
						"item": "1_1",
						"word": "zeteecoe",
						"shape": "1",
						"color": "1"
					},
					{
						"item": "2_2",
						"word": "gafykoe",
						"shape": "2",
						"color": "2"
					},
					{
						"item": "0_3",
						"word": "buvyckow",
						"shape": "0",
						"color": "3"
					},
					{
						"item": "2_0",
						"word": "gafeecow",
						"shape": "2",
						"color": "0"
					}
				],
				"test_trial": {
					"item": "1_0",
					"word": "zetickoe",
					"shape": "1",
					"color": "0",
					"catch_trial": true,
					"max_response_time": 20000
				},
				"exposure_time": 2000,
				"pause_time": 500,
				"progress": 0.21897810218978103
			}
		},
		{
			"event": "training_block",
			"payload": {
				"training_trials": [
					{
						"item": "1_3",
						"word": "zeteeckoh",
						"shape": "1",
						"color": "3"
					},
					{
						"item": "0_2",
						"word": "buvykow",
						"shape": "0",
						"color": "2"
					},
					{
						"item": "3_1",
						"word": "wopeeckoe",
						"shape": "3",
						"color": "1"
					},
					{
						"item": "1_2",
						"word": "zeteekow",
						"shape": "1",
						"color": "2"
					}
				],
				"test_trial": {
					"item": "0_1",
					"word": "buvikow",
					"shape": "0",
					"color": "1",
					"catch_trial": false,
					"max_response_time": 20000
				},
				"exposure_time": 2000,
				"pause_time": 500,
				"progress": 0.23722627737226276
			}
		},
		{
			"event": "training_block",
			"payload": {
				"training_trials": [
					{
						"item": "0_2",
						"word": "buvykow",
						"shape": "0",
						"color": "2"
					},
					{
						"item": "1_0",
						"word": "zetickoe",
						"shape": "1",
						"color": "0"
					},
					{
						"item": "2_2",
						"word": "gafykoe",
						"shape": "2",
						"color": "2"
					},
					{
						"item": "3_3",
						"word": "wopikoh",
						"shape": "3",
						"color": "3"
					}
				],
				"test_trial": {
					"item": "3_3",
					"word": "wopikoh",
					"shape": "3",
					"color": "3",
					"catch_trial": false,
					"max_response_time": 20000
				},
				"exposure_time": 2000,
				"pause_time": 500,
				"progress": 0.25547445255474455
			}
		},
		{
			"event": "training_block",
			"payload": {
				"training_trials": [
					{
						"item": "0_1",
						"word": "buvikow",
						"shape": "0",
						"color": "1"
					},
					{
						"item": "2_0",
						"word": "gafeecow",
						"shape": "2",
						"color": "0"
					},
					{
						"item": "1_3",
						"word": "zeteeckoh",
						"shape": "1",
						"color": "3"
					},
					{
						"item": "2_1",
						"word": "gafeecoh",
						"shape": "2",
						"color": "1"
					}
				],
				"test_trial": {
					"item": "1_3",
					"word": "zeteeckoh",
					"shape": "1",
					"color": "3",
					"catch_trial": false,
					"max_response_time": 20000
				},
				"exposure_time": 2000,
				"pause_time": 500,
				"progress": 0.2737226277372263
			}
		},
		{
			"event": "training_block",
			"payload": {
				"training_trials": [
					{
						"item": "1_2",
						"word": "zeteekow",
						"shape": "1",
						"color": "2"
					},
					{
						"item": "0_3",
						"word": "buvyckow",
						"shape": "0",
						"color": "3"
					},
					{
						"item": "3_1",
						"word": "wopeeckoe",
						"shape": "3",
						"color": "1"
					},
					{
						"item": "1_1",
						"word": "zeteecoe",
						"shape": "1",
						"color": "1"
					}
				],
				"test_trial": {
					"item": "2_1",
					"word": "gafeecoh",
					"shape": "2",
					"color": "1",
					"catch_trial": false,
					"max_response_time": 20000
				},
				"exposure_time": 2000,
				"pause_time": 500,
				"progress": 0.291970802919708
			}
		},
		{
			"event": "training_block",
			"payload": {
				"training_trials": [
					{
						"item": "2_2",
						"word": "gafykoe",
						"shape": "2",
						"color": "2"
					},
					{
						"item": "1_3",
						"word": "zeteeckoh",
						"shape": "1",
						"color": "3"
					},
					{
						"item": "1_1",
						"word": "zeteecoe",
						"shape": "1",
						"color": "1"
					},
					{
						"item": "2_1",
						"word": "gafeecoh",
						"shape": "2",
						"color": "1"
					}
				],
				"test_trial": {
					"item": "0_1",
					"word": "buvikow",
					"shape": "0",
					"color": "1",
					"catch_trial": false,
					"max_response_time": 20000
				},
				"exposure_time": 2000,
				"pause_time": 500,
				"progress": 0.3102189781021898
			}
		},
		{
			"event": "training_block",
			"payload": {
				"training_trials": [
					{
						"item": "3_3",
						"word": "wopikoh",
						"shape": "3",
						"color": "3"
					},
					{
						"item": "1_0",
						"word": "zetickoe",
						"shape": "1",
						"color": "0"
					},
					{
						"item": "0_2",
						"word": "buvykow",
						"shape": "0",
						"color": "2"
					},
					{
						"item": "2_0",
						"word": "gafeecow",
						"shape": "2",
						"color": "0"
					}
				],
				"test_trial": {
					"item": "1_0",
					"word": "zetickoe",
					"shape": "1",
					"color": "0",
					"catch_trial": false,
					"max_response_time": 20000
				},
				"exposure_time": 2000,
				"pause_time": 500,
				"progress": 0.3284671532846715
			}
		},
		{
			"event": "training_block",
			"payload": {
				"training_trials": [
					{
						"item": "1_2",
						"word": "zeteekow",
						"shape": "1",
						"color": "2"
					},
					{
						"item": "3_1",
						"word": "wopeeckoe",
						"shape": "3",
						"color": "1"
					},
					{
						"item": "0_1",
						"word": "buvikow",
						"shape": "0",
						"color": "1"
					},
					{
						"item": "0_3",
						"word": "buvyckow",
						"shape": "0",
						"color": "3"
					}
				],
				"test_trial": {
					"item": "1_2",
					"word": "zeteekow",
					"shape": "1",
					"color": "2",
					"catch_trial": false,
					"max_response_time": 20000
				},
				"exposure_time": 2000,
				"pause_time": 500,
				"progress": 0.3467153284671533
			}
		},
		{
			"event": "training_block",
			"payload": {
				"training_trials": [
					{
						"item": "3_1",
						"word": "wopeeckoe",
						"shape": "3",
						"color": "1"
					},
					{
						"item": "1_1",
						"word": "zeteecoe",
						"shape": "1",
						"color": "1"
					},
					{
						"item": "2_0",
						"word": "gafeecow",
						"shape": "2",
						"color": "0"
					},
					{
						"item": "0_2",
						"word": "buvykow",
						"shape": "0",
						"color": "2"
					}
				],
				"test_trial": {
					"item": "3_1",
					"word": "wopeeckoe",
					"shape": "3",
					"color": "1",
					"catch_trial": false,
					"max_response_time": 20000
				},
				"exposure_time": 2000,
				"pause_time": 500,
				"progress": 0.36496350364963503
			}
		},
		{
			"event": "training_block",
			"payload": {
				"training_trials": [
					{
						"item": "2_1",
						"word": "gafeecoh",
						"shape": "2",
						"color": "1"
					},
					{
						"item": "3_3",
						"word": "wopikoh",
						"shape": "3",
						"color": "3"
					},
					{
						"item": "1_0",
						"word": "zetickoe",
						"shape": "1",
						"color": "0"
					},
					{
						"item": "2_2",
						"word": "gafykoe",
						"shape": "2",
						"color": "2"
					}
				],
				"test_trial": {
					"item": "1_1",
					"word": "zeteecoe",
					"shape": "1",
					"color": "1",
					"catch_trial": false,
					"max_response_time": 20000
				},
				"exposure_time": 2000,
				"pause_time": 500,
				"progress": 0.38321167883211676
			}
		},
		{
			"event": "training_block",
			"payload": {
				"training_trials": [
					{
						"item": "1_2",
						"word": "zeteekow",
						"shape": "1",
						"color": "2"
					},
					{
						"item": "0_3",
						"word": "buvyckow",
						"shape": "0",
						"color": "3"
					},
					{
						"item": "1_3",
						"word": "zeteeckoh",
						"shape": "1",
						"color": "3"
					},
					{
						"item": "0_1",
						"word": "buvikow",
						"shape": "0",
						"color": "1"
					}
				],
				"test_trial": {
					"item": "2_0",
					"word": "gafeecow",
					"shape": "2",
					"color": "0",
					"catch_trial": false,
					"max_response_time": 20000
				},
				"exposure_time": 2000,
				"pause_time": 500,
				"progress": 0.40145985401459855
			}
		},
		{
			"event": "training_block",
			"payload": {
				"training_trials": [
					{
						"item": "1_3",
						"word": "zeteeckoh",
						"shape": "1",
						"color": "3"
					},
					{
						"item": "3_3",
						"word": "wopikoh",
						"shape": "3",
						"color": "3"
					},
					{
						"item": "1_1",
						"word": "zeteecoe",
						"shape": "1",
						"color": "1"
					},
					{
						"item": "2_0",
						"word": "gafeecow",
						"shape": "2",
						"color": "0"
					}
				],
				"test_trial": {
					"item": "2_2",
					"word": "gafykoe",
					"shape": "2",
					"color": "2",
					"catch_trial": false,
					"max_response_time": 20000
				},
				"exposure_time": 2000,
				"pause_time": 500,
				"progress": 0.4197080291970803
			}
		},
		{
			"event": "training_block",
			"payload": {
				"training_trials": [
					{
						"item": "1_2",
						"word": "zeteekow",
						"shape": "1",
						"color": "2"
					},
					{
						"item": "0_1",
						"word": "buvikow",
						"shape": "0",
						"color": "1"
					},
					{
						"item": "3_1",
						"word": "wopeeckoe",
						"shape": "3",
						"color": "1"
					},
					{
						"item": "0_2",
						"word": "buvykow",
						"shape": "0",
						"color": "2"
					}
				],
				"test_trial": {
					"item": "0_2",
					"word": "buvykow",
					"shape": "0",
					"color": "2",
					"catch_trial": true,
					"max_response_time": 20000
				},
				"exposure_time": 2000,
				"pause_time": 500,
				"progress": 0.43795620437956206
			}
		},
		{
			"event": "training_block",
			"payload": {
				"training_trials": [
					{
						"item": "1_0",
						"word": "zetickoe",
						"shape": "1",
						"color": "0"
					},
					{
						"item": "2_1",
						"word": "gafeecoh",
						"shape": "2",
						"color": "1"
					},
					{
						"item": "2_2",
						"word": "gafykoe",
						"shape": "2",
						"color": "2"
					},
					{
						"item": "0_3",
						"word": "buvyckow",
						"shape": "0",
						"color": "3"
					}
				],
				"test_trial": {
					"item": "0_3",
					"word": "buvyckow",
					"shape": "0",
					"color": "3",
					"catch_trial": false,
					"max_response_time": 20000
				},
				"exposure_time": 2000,
				"pause_time": 500,
				"progress": 0.4562043795620438
			}
		},
		{
			"event": "training_block",
			"payload": {
				"training_trials": [
					{
						"item": "2_0",
						"word": "gafeecow",
						"shape": "2",
						"color": "0"
					},
					{
						"item": "0_1",
						"word": "buvikow",
						"shape": "0",
						"color": "1"
					},
					{
						"item": "0_3",
						"word": "buvyckow",
						"shape": "0",
						"color": "3"
					},
					{
						"item": "3_1",
						"word": "wopeeckoe",
						"shape": "3",
						"color": "1"
					}
				],
				"test_trial": {
					"item": "3_1",
					"word": "wopeeckoe",
					"shape": "3",
					"color": "1",
					"catch_trial": false,
					"max_response_time": 20000
				},
				"exposure_time": 2000,
				"pause_time": 500,
				"progress": 0.4744525547445255
			}
		},
		{
			"event": "training_block",
			"payload": {
				"training_trials": [
					{
						"item": "1_1",
						"word": "zeteecoe",
						"shape": "1",
						"color": "1"
					},
					{
						"item": "1_3",
						"word": "zeteeckoh",
						"shape": "1",
						"color": "3"
					},
					{
						"item": "2_2",
						"word": "gafykoe",
						"shape": "2",
						"color": "2"
					},
					{
						"item": "3_3",
						"word": "wopikoh",
						"shape": "3",
						"color": "3"
					}
				],
				"test_trial": {
					"item": "1_3",
					"word": "zeteeckoh",
					"shape": "1",
					"color": "3",
					"catch_trial": false,
					"max_response_time": 20000
				},
				"exposure_time": 2000,
				"pause_time": 500,
				"progress": 0.4927007299270073
			}
		},
		{
			"event": "training_block",
			"payload": {
				"training_trials": [
					{
						"item": "2_1",
						"word": "gafeecoh",
						"shape": "2",
						"color": "1"
					},
					{
						"item": "1_0",
						"word": "zetickoe",
						"shape": "1",
						"color": "0"
					},
					{
						"item": "1_2",
						"word": "zeteekow",
						"shape": "1",
						"color": "2"
					},
					{
						"item": "0_2",
						"word": "buvykow",
						"shape": "0",
						"color": "2"
					}
				],
				"test_trial": {
					"item": "2_1",
					"word": "gafeecoh",
					"shape": "2",
					"color": "1",
					"catch_trial": false,
					"max_response_time": 20000
				},
				"exposure_time": 2000,
				"pause_time": 500,
				"progress": 0.5109489051094891
			}
		},
		{
			"event": "training_block",
			"payload": {
				"training_trials": [
					{
						"item": "0_1",
						"word": "buvikow",
						"shape": "0",
						"color": "1"
					},
					{
						"item": "1_2",
						"word": "zeteekow",
						"shape": "1",
						"color": "2"
					},
					{
						"item": "0_2",
						"word": "buvykow",
						"shape": "0",
						"color": "2"
					},
					{
						"item": "2_1",
						"word": "gafeecoh",
						"shape": "2",
						"color": "1"
					}
				],
				"test_trial": {
					"item": "2_0",
					"word": "gafeecow",
					"shape": "2",
					"color": "0",
					"catch_trial": false,
					"max_response_time": 20000
				},
				"exposure_time": 2000,
				"pause_time": 500,
				"progress": 0.5291970802919708
			}
		},
		{
			"event": "training_block",
			"payload": {
				"training_trials": [
					{
						"item": "3_1",
						"word": "wopeeckoe",
						"shape": "3",
						"color": "1"
					},
					{
						"item": "0_3",
						"word": "buvyckow",
						"shape": "0",
						"color": "3"
					},
					{
						"item": "1_3",
						"word": "zeteeckoh",
						"shape": "1",
						"color": "3"
					},
					{
						"item": "1_0",
						"word": "zetickoe",
						"shape": "1",
						"color": "0"
					}
				],
				"test_trial": {
					"item": "1_0",
					"word": "zetickoe",
					"shape": "1",
					"color": "0",
					"catch_trial": false,
					"max_response_time": 20000
				},
				"exposure_time": 2000,
				"pause_time": 500,
				"progress": 0.5474452554744526
			}
		},
		{
			"event": "training_block",
			"payload": {
				"training_trials": [
					{
						"item": "3_3",
						"word": "wopikoh",
						"shape": "3",
						"color": "3"
					},
					{
						"item": "1_1",
						"word": "zeteecoe",
						"shape": "1",
						"color": "1"
					},
					{
						"item": "2_2",
						"word": "gafykoe",
						"shape": "2",
						"color": "2"
					},
					{
						"item": "2_0",
						"word": "gafeecow",
						"shape": "2",
						"color": "0"
					}
				],
				"test_trial": {
					"item": "2_2",
					"word": "gafykoe",
					"shape": "2",
					"color": "2",
					"catch_trial": false,
					"max_response_time": 20000
				},
				"exposure_time": 2000,
				"pause_time": 500,
				"progress": 0.5656934306569343
			}
		},
		{
			"event": "training_block",
			"payload": {
				"training_trials": [
					{
						"item": "0_2",
						"word": "buvykow",
						"shape": "0",
						"color": "2"
					},
					{
						"item": "3_3",
						"word": "wopikoh",
						"shape": "3",
						"color": "3"
					},
					{
						"item": "1_1",
						"word": "zeteecoe",
						"shape": "1",
						"color": "1"
					},
					{
						"item": "0_1",
						"word": "buvikow",
						"shape": "0",
						"color": "1"
					}
				],
				"test_trial": {
					"item": "0_3",
					"word": "buvyckow",
					"shape": "0",
					"color": "3",
					"catch_trial": false,
					"max_response_time": 20000
				},
				"exposure_time": 2000,
				"pause_time": 500,
				"progress": 0.583941605839416
			}
		},
		{
			"event": "training_block",
			"payload": {
				"training_trials": [
					{
						"item": "1_3",
						"word": "zeteeckoh",
						"shape": "1",
						"color": "3"
					},
					{
						"item": "1_2",
						"word": "zeteekow",
						"shape": "1",
						"color": "2"
					},
					{
						"item": "0_3",
						"word": "buvyckow",
						"shape": "0",
						"color": "3"
					},
					{
						"item": "2_1",
						"word": "gafeecoh",
						"shape": "2",
						"color": "1"
					}
				],
				"test_trial": {
					"item": "0_1",
					"word": "buvikow",
					"shape": "0",
					"color": "1",
					"catch_trial": false,
					"max_response_time": 20000
				},
				"exposure_time": 2000,
				"pause_time": 500,
				"progress": 0.6021897810218978
			}
		},
		{
			"event": "training_block",
			"payload": {
				"training_trials": [
					{
						"item": "1_0",
						"word": "zetickoe",
						"shape": "1",
						"color": "0"
					},
					{
						"item": "3_1",
						"word": "wopeeckoe",
						"shape": "3",
						"color": "1"
					},
					{
						"item": "2_2",
						"word": "gafykoe",
						"shape": "2",
						"color": "2"
					},
					{
						"item": "2_0",
						"word": "gafeecow",
						"shape": "2",
						"color": "0"
					}
				],
				"test_trial": {
					"item": "0_2",
					"word": "buvykow",
					"shape": "0",
					"color": "2",
					"catch_trial": false,
					"max_response_time": 20000
				},
				"exposure_time": 2000,
				"pause_time": 500,
				"progress": 0.6204379562043796
			}
		},
		{
			"event": "training_block",
			"payload": {
				"training_trials": [
					{
						"item": "1_3",
						"word": "zeteeckoh",
						"shape": "1",
						"color": "3"
					},
					{
						"item": "2_0",
						"word": "gafeecow",
						"shape": "2",
						"color": "0"
					},
					{
						"item": "2_1",
						"word": "gafeecoh",
						"shape": "2",
						"color": "1"
					},
					{
						"item": "0_3",
						"word": "buvyckow",
						"shape": "0",
						"color": "3"
					}
				],
				"test_trial": {
					"item": "1_1",
					"word": "zeteecoe",
					"shape": "1",
					"color": "1",
					"catch_trial": false,
					"max_response_time": 20000
				},
				"exposure_time": 2000,
				"pause_time": 500,
				"progress": 0.6386861313868614
			}
		},
		{
			"event": "training_block",
			"payload": {
				"training_trials": [
					{
						"item": "0_1",
						"word": "buvikow",
						"shape": "0",
						"color": "1"
					},
					{
						"item": "2_2",
						"word": "gafykoe",
						"shape": "2",
						"color": "2"
					},
					{
						"item": "1_0",
						"word": "zetickoe",
						"shape": "1",
						"color": "0"
					},
					{
						"item": "0_2",
						"word": "buvykow",
						"shape": "0",
						"color": "2"
					}
				],
				"test_trial": {
					"item": "3_3",
					"word": "wopikoh",
					"shape": "3",
					"color": "3",
					"catch_trial": true,
					"max_response_time": 20000
				},
				"exposure_time": 2000,
				"pause_time": 500,
				"progress": 0.656934306569343
			}
		},
		{
			"event": "training_block",
			"payload": {
				"training_trials": [
					{
						"item": "3_1",
						"word": "wopeeckoe",
						"shape": "3",
						"color": "1"
					},
					{
						"item": "1_2",
						"word": "zeteekow",
						"shape": "1",
						"color": "2"
					},
					{
						"item": "3_3",
						"word": "wopikoh",
						"shape": "3",
						"color": "3"
					},
					{
						"item": "1_1",
						"word": "zeteecoe",
						"shape": "1",
						"color": "1"
					}
				],
				"test_trial": {
					"item": "1_2",
					"word": "zeteekow",
					"shape": "1",
					"color": "2",
					"catch_trial": false,
					"max_response_time": 20000
				},
				"exposure_time": 2000,
				"pause_time": 500,
				"progress": 0.6751824817518248
			}
		},
		{
			"event": "instructions",
			"payload": {
				"instruction_screen": "test",
				"instruction_time": 5000,
				"response_kind": "next",
				"progress": 0.6934306569343066
			}
		},
		{
			"event": "test_production",
			"payload": {
				"item": "1_2",
				"word": "zeteekow",
				"shape": "1",
				"color": "2",
				"pause_time": 500,
				"progress": 0.7299270072992701
			}
		},
		{
			"event": "test_comprehension",
			"payload": {
				"word": "wopeeckoe",
				"items": [
					"3_1"
				],
				"array": [
					"3_0",
					"0_1",
					"1_3",
					"2_2",
					"1_1",
					"0_3",
					"3_2",
					"3_1",
					"0_0",
					"1_2",
					"3_3",
					"2_0",
					"0_2",
					"1_0",
					"2_3",
					"2_1"
				],
				"pause_time": 500,
				"progress": 0.7372262773722628
			}
		},
		{
			"event": "test_production",
			"payload": {
				"item": "2_1",
				"word": "gafeecoh",
				"shape": "2",
				"color": "1",
				"pause_time": 500,
				"progress": 0.7445255474452555
			}
		},
		{
			"event": "test_comprehension",
			"payload": {
				"word": "zeteeckoh",
				"items": [
					"1_3"
				],
				"array": [
					"3_3",
					"3_2",
					"2_3",
					"3_1",
					"2_1",
					"1_1",
					"0_0",
					"3_0",
					"1_3",
					"0_1",
					"2_2",
					"2_0",
					"1_2",
					"1_0",
					"0_3",
					"0_2"
				],
				"pause_time": 500,
				"progress": 0.7518248175182481
			}
		},
		{
			"event": "test_production",
			"payload": {
				"item": "0_1",
				"word": "buvikow",
				"shape": "0",
				"color": "1",
				"pause_time": 500,
				"progress": 0.7591240875912408
			}
		},
		{
			"event": "test_comprehension",
			"payload": {
				"word": "wopickoe",
				"items": [
					"3_0"
				],
				"array": [
					"2_3",
					"3_0",
					"1_1",
					"0_1",
					"1_3",
					"3_3",
					"2_2",
					"1_0",
					"0_2",
					"2_0",
					"2_1",
					"0_3",
					"1_2",
					"3_1",
					"3_2",
					"0_0"
				],
				"pause_time": 500,
				"progress": 0.7664233576642335
			}
		},
		{
			"event": "test_production",
			"payload": {
				"item": "3_1",
				"word": "wopeeckoe",
				"shape": "3",
				"color": "1",
				"pause_time": 500,
				"progress": 0.7737226277372263
			}
		},
		{
			"event": "test_comprehension",
			"payload": {
				"word": "zeteecoe",
				"items": [
					"1_1"
				],
				"array": [
					"1_0",
					"2_2",
					"3_0",
					"1_2",
					"2_3",
					"3_1",
					"3_2",
					"0_3",
					"0_2",
					"0_0",
					"3_3",
					"1_3",
					"2_1",
					"2_0",
					"1_1",
					"0_1"
				],
				"pause_time": 500,
				"progress": 0.781021897810219
			}
		},
		{
			"event": "test_production",
			"payload": {
				"item": "0_2",
				"word": "buvykow",
				"shape": "0",
				"color": "2",
				"pause_time": 500,
				"progress": 0.7883211678832117
			}
		},
		{
			"event": "test_comprehension",
			"payload": {
				"word": "buvikow",
				"items": [
					"0_1"
				],
				"array": [
					"2_3",
					"0_3",
					"3_2",
					"1_2",
					"1_1",
					"0_1",
					"1_3",
					"2_2",
					"2_1",
					"3_3",
					"3_0",
					"2_0",
					"0_0",
					"0_2",
					"1_0",
					"3_1"
				],
				"pause_time": 500,
				"progress": 0.7956204379562044
			}
		},
		{
			"event": "test_production",
			"payload": {
				"item": "0_3",
				"word": "buvyckow",
				"shape": "0",
				"color": "3",
				"pause_time": 500,
				"progress": 0.8029197080291971
			}
		},
		{
			"event": "test_comprehension",
			"payload": {
				"word": "zeteekow",
				"items": [
					"1_2"
				],
				"array": [
					"2_0",
					"3_0",
					"2_2",
					"1_0",
					"0_1",
					"3_1",
					"3_2",
					"3_3",
					"2_3",
					"0_3",
					"1_1",
					"2_1",
					"1_3",
					"0_2",
					"1_2",
					"0_0"
				],
				"pause_time": 500,
				"progress": 0.8102189781021898
			}
		},
		{
			"event": "test_production",
			"payload": {
				"item": "1_3",
				"word": "zeteeckoh",
				"shape": "1",
				"color": "3",
				"pause_time": 500,
				"progress": 0.8175182481751825
			}
		},
		{
			"event": "test_comprehension",
			"payload": {
				"word": "buvykow",
				"items": [
					"0_2"
				],
				"array": [
					"3_2",
					"1_0",
					"1_3",
					"2_2",
					"0_0",
					"0_1",
					"2_3",
					"2_1",
					"1_2",
					"3_1",
					"2_0",
					"3_3",
					"1_1",
					"0_3",
					"0_2",
					"3_0"
				],
				"pause_time": 500,
				"progress": 0.8248175182481752
			}
		},
		{
			"event": "test_production",
			"payload": {
				"item": "2_2",
				"word": "gafykoe",
				"shape": "2",
				"color": "2",
				"pause_time": 500,
				"progress": 0.8321167883211679
			}
		},
		{
			"event": "test_comprehension",
			"payload": {
				"word": "wopyckoe",
				"items": [
					"3_2"
				],
				"array": [
					"2_0",
					"1_0",
					"0_1",
					"2_3",
					"0_3",
					"3_3",
					"1_1",
					"3_1",
					"0_2",
					"1_3",
					"0_0",
					"3_0",
					"1_2",
					"3_2",
					"2_1",
					"2_2"
				],
				"pause_time": 500,
				"progress": 0.8394160583941606
			}
		},
		{
			"event": "test_production",
			"payload": {
				"item": "2_0",
				"word": "gafeecow",
				"shape": "2",
				"color": "0",
				"pause_time": 500,
				"progress": 0.8467153284671532
			}
		},
		{
			"event": "test_comprehension",
			"payload": {
				"word": "buvecow",
				"items": [
					"0_0"
				],
				"array": [
					"2_0",
					"1_2",
					"3_2",
					"1_0",
					"0_3",
					"2_1",
					"2_3",
					"3_1",
					"1_3",
					"0_1",
					"0_0",
					"3_3",
					"0_2",
					"1_1",
					"2_2",
					"3_0"
				],
				"pause_time": 500,
				"progress": 0.8540145985401459
			}
		},
		{
			"event": "test_production",
			"payload": {
				"item": "1_0",
				"word": "zetickoe",
				"shape": "1",
				"color": "0",
				"pause_time": 500,
				"progress": 0.8613138686131386
			}
		},
		{
			"event": "test_comprehension",
			"payload": {
				"word": "zetickoe",
				"items": [
					"1_0"
				],
				"array": [
					"2_0",
					"1_3",
					"0_1",
					"1_2",
					"2_3",
					"1_0",
					"1_1",
					"0_2",
					"2_2",
					"0_0",
					"3_3",
					"3_1",
					"3_2",
					"3_0",
					"0_3",
					"2_1"
				],
				"pause_time": 500,
				"progress": 0.8686131386861314
			}
		},
		{
			"event": "test_production",
			"payload": {
				"item": "3_0",
				"word": "wopickoe",
				"shape": "3",
				"color": "0",
				"pause_time": 500,
				"progress": 0.8759124087591241
			}
		},
		{
			"event": "test_comprehension",
			"payload": {
				"word": "gafykoe",
				"items": [
					"2_2"
				],
				"array": [
					"3_0",
					"2_3",
					"0_3",
					"0_1",
					"0_0",
					"2_0",
					"2_2",
					"2_1",
					"3_1",
					"1_2",
					"1_3",
					"1_0",
					"3_2",
					"0_2",
					"3_3",
					"1_1"
				],
				"pause_time": 500,
				"progress": 0.8832116788321168
			}
		},
		{
			"event": "test_production",
			"payload": {
				"item": "3_3",
				"word": "wopikoh",
				"shape": "3",
				"color": "3",
				"pause_time": 500,
				"progress": 0.8905109489051095
			}
		},
		{
			"event": "test_comprehension",
			"payload": {
				"word": "buvyckow",
				"items": [
					"0_3"
				],
				"array": [
					"2_0",
					"1_3",
					"1_2",
					"3_1",
					"0_1",
					"2_2",
					"3_2",
					"1_1",
					"2_3",
					"2_1",
					"3_0",
					"0_2",
					"0_3",
					"1_0",
					"0_0",
					"3_3"
				],
				"pause_time": 500,
				"progress": 0.8978102189781022
			}
		},
		{
			"event": "test_production",
			"payload": {
				"item": "3_2",
				"word": "wopyckoe",
				"shape": "3",
				"color": "2",
				"pause_time": 500,
				"progress": 0.9051094890510949
			}
		},
		{
			"event": "test_comprehension",
			"payload": {
				"word": "gafeecoh",
				"items": [
					"2_1"
				],
				"array": [
					"0_3",
					"3_2",
					"2_2",
					"1_3",
					"3_1",
					"0_0",
					"2_0",
					"1_2",
					"2_1",
					"0_2",
					"3_0",
					"2_3",
					"1_1",
					"3_3",
					"0_1",
					"1_0"
				],
				"pause_time": 500,
				"progress": 0.9124087591240876
			}
		},
		{
			"event": "test_production",
			"payload": {
				"item": "2_3",
				"word": "gafeeckoh",
				"shape": "2",
				"color": "3",
				"pause_time": 500,
				"progress": 0.9197080291970803
			}
		},
		{
			"event": "test_comprehension",
			"payload": {
				"word": "gafeeckoh",
				"items": [
					"2_3"
				],
				"array": [
					"2_2",
					"1_1",
					"2_0",
					"1_2",
					"1_0",
					"3_3",
					"2_1",
					"0_2",
					"0_3",
					"3_0",
					"2_3",
					"0_0",
					"3_1",
					"1_3",
					"0_1",
					"3_2"
				],
				"pause_time": 500,
				"progress": 0.927007299270073
			}
		},
		{
			"event": "test_production",
			"payload": {
				"item": "0_0",
				"word": "buvecow",
				"shape": "0",
				"color": "0",
				"pause_time": 500,
				"progress": 0.9343065693430657
			}
		},
		{
			"event": "test_comprehension",
			"payload": {
				"word": "wopikoh",
				"items": [
					"3_3"
				],
				"array": [
					"0_3",
					"2_1",
					"3_0",
					"1_3",
					"2_3",
					"2_0",
					"2_2",
					"3_3",
					"3_1",
					"0_2",
					"1_0",
					"0_0",
					"3_2",
					"0_1",
					"1_2",
					"1_1"
				],
				"pause_time": 500,
				"progress": 0.9416058394160584
			}
		},
		{
			"event": "test_production",
			"payload": {
				"item": "1_1",
				"word": "zeteecoe",
				"shape": "1",
				"color": "1",
				"pause_time": 500,
				"progress": 0.948905109489051
			}
		},
		{
			"event": "test_comprehension",
			"payload": {
				"word": "gafeecow",
				"items": [
					"2_0"
				],
				"array": [
					"0_2",
					"2_2",
					"1_2",
					"3_0",
					"2_3",
					"2_0",
					"1_0",
					"3_3",
					"0_0",
					"3_1",
					"0_3",
					"1_1",
					"1_3",
					"3_2",
					"2_1",
					"0_1"
				],
				"pause_time": 500,
				"progress": 0.9562043795620438
			}
		},
		{
			"event": "questionnaire",
			"payload": {
				"progress": 0.9635036496350365
			}
		},
		{
			"event": "end_of_experiment",
			"payload": {
				"return_url": "https://app.prolific.co/submissions/complete?cc=CJ7QYYRQ",
				"basic_pay": 300,
				"progress": 1
			}
		}
	],
	"n_reinitializations": 0,
	"sequence_position": 73,
	"total_bonus": 117,
	"responses": [
		{
			"test_type": "mini_test",
			"shape": "3",
			"color": "3",
			"expected_label": "wopikoh",
			"catch_trial": false,
			"input_label": "wopikoh",
			"response_time": 8559,
			"object_clicked": false,
			"time": 1683213039
		},
		{
			"test_type": "mini_test",
			"shape": "2",
			"color": "2",
			"expected_label": "gafykoe",
			"catch_trial": false,
			"input_label": "gafykoe",
			"response_time": 6538,
			"object_clicked": false,
			"time": 1683213055
		},
		{
			"test_type": "mini_test",
			"shape": "0",
			"color": "2",
			"expected_label": "buvykow",
			"catch_trial": false,
			"input_label": "buvyckow",
			"response_time": 5762,
			"object_clicked": false,
			"time": 1683213070
		},
		{
			"test_type": "mini_test",
			"shape": "1",
			"color": "3",
			"expected_label": "zeteeckoh",
			"catch_trial": false,
			"input_label": "zeteeckoh",
			"response_time": 6869,
			"object_clicked": false,
			"time": 1683213087
		},
		{
			"test_type": "mini_test",
			"shape": "0",
			"color": "3",
			"expected_label": "buvyckow",
			"catch_trial": false,
			"input_label": "buvyckow",
			"response_time": 6880,
			"object_clicked": false,
			"time": 1683213103
		},
		{
			"test_type": "mini_test",
			"shape": "3",
			"color": "1",
			"expected_label": "wopeeckoe",
			"catch_trial": false,
			"input_label": "wopeeckoe",
			"response_time": 5526,
			"object_clicked": false,
			"time": 1683213119
		},
		{
			"test_type": "mini_test",
			"shape": "2",
			"color": "0",
			"expected_label": "gafeecow",
			"catch_trial": false,
			"input_label": "gafeecow",
			"response_time": 5108,
			"object_clicked": false,
			"time": 1683213133
		},
		{
			"test_type": "mini_test",
			"shape": "1",
			"color": "2",
			"expected_label": "zeteekow",
			"catch_trial": false,
			"input_label": "zeteekow",
			"response_time": 5257,
			"object_clicked": false,
			"time": 1683213148
		},
		{
			"test_type": "mini_test",
			"shape": "2",
			"color": "1",
			"expected_label": "gafeecoh",
			"catch_trial": false,
			"input_label": "gafeecoh",
			"response_time": 6200,
			"object_clicked": false,
			"time": 1683213164
		},
		{
			"test_type": "mini_test",
			"shape": "1",
			"color": "1",
			"expected_label": "zeteecoe",
			"catch_trial": false,
			"input_label": "zeteecoe",
			"response_time": 3912,
			"object_clicked": false,
			"time": 1683213177
		},
		{
			"test_type": "mini_test",
			"shape": "1",
			"color": "0",
			"expected_label": "zetickoe",
			"catch_trial": true,
			"input_label": "zetickoe",
			"response_time": 15776,
			"object_clicked": true,
			"time": 1683213203
		},
		{
			"test_type": "mini_test",
			"shape": "0",
			"color": "1",
			"expected_label": "buvikow",
			"catch_trial": false,
			"input_label": "buvikow",
			"response_time": 5873,
			"object_clicked": false,
			"time": 1683213218
		},
		{
			"test_type": "mini_test",
			"shape": "3",
			"color": "3",
			"expected_label": "wopikoh",
			"catch_trial": false,
			"input_label": "wopikoh",
			"response_time": 5741,
			"object_clicked": false,
			"time": 1683213234
		},
		{
			"test_type": "mini_test",
			"shape": "1",
			"color": "3",
			"expected_label": "zeteeckoh",
			"catch_trial": false,
			"input_label": "zeteeckoh",
			"response_time": 4064,
			"object_clicked": false,
			"time": 1683213247
		},
		{
			"test_type": "mini_test",
			"shape": "2",
			"color": "1",
			"expected_label": "gafeecoh",
			"catch_trial": false,
			"input_label": "gafeecoh",
			"response_time": 3839,
			"object_clicked": false,
			"time": 1683213261
		},
		{
			"test_type": "mini_test",
			"shape": "0",
			"color": "1",
			"expected_label": "buvikow",
			"catch_trial": false,
			"input_label": "buvikow",
			"response_time": 3652,
			"object_clicked": false,
			"time": 1683213274
		},
		{
			"test_type": "mini_test",
			"shape": "1",
			"color": "0",
			"expected_label": "zetickoe",
			"catch_trial": false,
			"input_label": "zetickoe",
			"response_time": 6333,
			"object_clicked": false,
			"time": 1683213290
		},
		{
			"test_type": "mini_test",
			"shape": "1",
			"color": "2",
			"expected_label": "zeteekow",
			"catch_trial": false,
			"input_label": "zeteekow",
			"response_time": 4834,
			"object_clicked": false,
			"time": 1683213304
		},
		{
			"test_type": "mini_test",
			"shape": "3",
			"color": "1",
			"expected_label": "wopeeckoe",
			"catch_trial": false,
			"input_label": "wopeeckoe",
			"response_time": 4549,
			"object_clicked": false,
			"time": 1683213319
		},
		{
			"test_type": "mini_test",
			"shape": "1",
			"color": "1",
			"expected_label": "zeteecoe",
			"catch_trial": false,
			"input_label": "zeteecoe",
			"response_time": 5966,
			"object_clicked": false,
			"time": 1683213334
		},
		{
			"test_type": "mini_test",
			"shape": "2",
			"color": "0",
			"expected_label": "gafeecow",
			"catch_trial": false,
			"input_label": "gafeecow",
			"response_time": 9403,
			"object_clicked": false,
			"time": 1683213353
		},
		{
			"test_type": "mini_test",
			"shape": "2",
			"color": "2",
			"expected_label": "gafykoe",
			"catch_trial": false,
			"input_label": "gafykoe",
			"response_time": 8932,
			"object_clicked": false,
			"time": 1683213372
		},
		{
			"test_type": "mini_test",
			"shape": "0",
			"color": "2",
			"expected_label": "buvykow",
			"catch_trial": true,
			"input_label": "buvekow",
			"response_time": 9437,
			"object_clicked": true,
			"time": 1683213391
		},
		{
			"test_type": "mini_test",
			"shape": "0",
			"color": "3",
			"expected_label": "buvyckow",
			"catch_trial": false,
			"input_label": "buvyckow",
			"response_time": 3449,
			"object_clicked": false,
			"time": 1683213404
		},
		{
			"test_type": "mini_test",
			"shape": "3",
			"color": "1",
			"expected_label": "wopeeckoe",
			"catch_trial": false,
			"input_label": "wopeeckoe",
			"response_time": 4131,
			"object_clicked": false,
			"time": 1683213418
		},
		{
			"test_type": "mini_test",
			"shape": "1",
			"color": "3",
			"expected_label": "zeteeckoh",
			"catch_trial": false,
			"input_label": "zeteeckoh",
			"response_time": 4968,
			"object_clicked": false,
			"time": 1683213432
		},
		{
			"test_type": "mini_test",
			"shape": "2",
			"color": "1",
			"expected_label": "gafeecoh",
			"catch_trial": false,
			"input_label": "gafeecoh",
			"response_time": 11590,
			"object_clicked": false,
			"time": 1683213453
		},
		{
			"test_type": "mini_test",
			"shape": "2",
			"color": "0",
			"expected_label": "gafeecow",
			"catch_trial": false,
			"input_label": "gafeecow",
			"response_time": 7661,
			"object_clicked": false,
			"time": 1683213471
		},
		{
			"test_type": "mini_test",
			"shape": "1",
			"color": "0",
			"expected_label": "zetickoe",
			"catch_trial": false,
			"input_label": "zetickoe",
			"response_time": 8205,
			"object_clicked": false,
			"time": 1683213488
		},
		{
			"test_type": "mini_test",
			"shape": "2",
			"color": "2",
			"expected_label": "gafykoe",
			"catch_trial": false,
			"input_label": "gafykoe",
			"response_time": 10419,
			"object_clicked": false,
			"time": 1683213508
		},
		{
			"test_type": "mini_test",
			"shape": "0",
			"color": "3",
			"expected_label": "buvyckow",
			"catch_trial": false,
			"input_label": "buvyckow",
			"response_time": 7337,
			"object_clicked": false,
			"time": 1683213525
		},
		{
			"test_type": "mini_test",
			"shape": "0",
			"color": "1",
			"expected_label": "buvikow",
			"catch_trial": false,
			"input_label": "buvikow",
			"response_time": 7032,
			"object_clicked": false,
			"time": 1683213542
		},
		{
			"test_type": "mini_test",
			"shape": "0",
			"color": "2",
			"expected_label": "buvykow",
			"catch_trial": false,
			"input_label": "buvykoe",
			"response_time": 7402,
			"object_clicked": false,
			"time": 1683213559
		},
		{
			"test_type": "mini_test",
			"shape": "1",
			"color": "1",
			"expected_label": "zeteecoe",
			"catch_trial": false,
			"input_label": "zeteecoe",
			"response_time": 9631,
			"object_clicked": false,
			"time": 1683213578
		},
		{
			"test_type": "mini_test",
			"shape": "3",
			"color": "3",
			"expected_label": "wopikoh",
			"catch_trial": true,
			"input_label": "wopikoh",
			"response_time": 11074,
			"object_clicked": true,
			"time": 1683213599
		},
		{
			"test_type": "mini_test",
			"shape": "1",
			"color": "2",
			"expected_label": "zeteekow",
			"catch_trial": false,
			"input_label": "zeteekow",
			"response_time": 5197,
			"object_clicked": false,
			"time": 1683213614
		},
		{
			"test_type": "test_production",
			"shape": "1",
			"color": "2",
			"expected_label": "zeteekow",
			"input_label": "zeteekow",
			"response_time": 3299,
			"time": 1683213625
		},
		{
			"test_type": "test_comprehension",
			"word": "wopeeckoe",
			"items": [
				"3_1"
			],
			"array": [
				"3_0",
				"0_1",
				"1_3",
				"2_2",
				"1_1",
				"0_3",
				"3_2",
				"3_1",
				"0_0",
				"1_2",
				"3_3",
				"2_0",
				"0_2",
				"1_0",
				"2_3",
				"2_1"
			],
			"selected_button": 7,
			"selected_item": "3_1",
			"response_time": 12125,
			"time": 1683213638
		},
		{
			"test_type": "test_production",
			"shape": "2",
			"color": "1",
			"expected_label": "gafeecoh",
			"input_label": "gafeecoh",
			"response_time": 5254,
			"time": 1683213645
		},
		{
			"test_type": "test_comprehension",
			"word": "zeteeckoh",
			"items": [
				"1_3"
			],
			"array": [
				"3_3",
				"3_2",
				"2_3",
				"3_1",
				"2_1",
				"1_1",
				"0_0",
				"3_0",
				"1_3",
				"0_1",
				"2_2",
				"2_0",
				"1_2",
				"1_0",
				"0_3",
				"0_2"
			],
			"selected_button": 0,
			"selected_item": "3_3",
			"response_time": 5838,
			"time": 1683213652
		},
		{
			"test_type": "test_production",
			"shape": "0",
			"color": "1",
			"expected_label": "buvikow",
			"input_label": "buvikow",
			"response_time": 3913,
			"time": 1683213658
		},
		{
			"test_type": "test_comprehension",
			"word": "wopickoe",
			"items": [
				"3_0"
			],
			"array": [
				"2_3",
				"3_0",
				"1_1",
				"0_1",
				"1_3",
				"3_3",
				"2_2",
				"1_0",
				"0_2",
				"2_0",
				"2_1",
				"0_3",
				"1_2",
				"3_1",
				"3_2",
				"0_0"
			],
			"selected_button": 14,
			"selected_item": "3_2",
			"response_time": 8726,
			"time": 1683213668
		},
		{
			"test_type": "test_production",
			"shape": "3",
			"color": "1",
			"expected_label": "wopeeckoe",
			"input_label": "wopeeckoe",
			"response_time": 3383,
			"time": 1683213673
		},
		{
			"test_type": "test_comprehension",
			"word": "zeteecoe",
			"items": [
				"1_1"
			],
			"array": [
				"1_0",
				"2_2",
				"3_0",
				"1_2",
				"2_3",
				"3_1",
				"3_2",
				"0_3",
				"0_2",
				"0_0",
				"3_3",
				"1_3",
				"2_1",
				"2_0",
				"1_1",
				"0_1"
			],
			"selected_button": 14,
			"selected_item": "1_1",
			"response_time": 13704,
			"time": 1683213689
		},
		{
			"test_type": "test_production",
			"shape": "0",
			"color": "2",
			"expected_label": "buvykow",
			"input_label": "buvikoe",
			"response_time": 5509,
			"time": 1683213696
		},
		{
			"test_type": "test_comprehension",
			"word": "buvikow",
			"items": [
				"0_1"
			],
			"array": [
				"2_3",
				"0_3",
				"3_2",
				"1_2",
				"1_1",
				"0_1",
				"1_3",
				"2_2",
				"2_1",
				"3_3",
				"3_0",
				"2_0",
				"0_0",
				"0_2",
				"1_0",
				"3_1"
			],
			"selected_button": 5,
			"selected_item": "0_1",
			"response_time": 5645,
			"time": 1683213703
		},
		{
			"test_type": "test_production",
			"shape": "0",
			"color": "3",
			"expected_label": "buvyckow",
			"input_label": "buvyckow",
			"response_time": 4310,
			"time": 1683213709
		},
		{
			"test_type": "test_comprehension",
			"word": "zeteekow",
			"items": [
				"1_2"
			],
			"array": [
				"2_0",
				"3_0",
				"2_2",
				"1_0",
				"0_1",
				"3_1",
				"3_2",
				"3_3",
				"2_3",
				"0_3",
				"1_1",
				"2_1",
				"1_3",
				"0_2",
				"1_2",
				"0_0"
			],
			"selected_button": 14,
			"selected_item": "1_2",
			"response_time": 6648,
			"time": 1683213717
		},
		{
			"test_type": "test_production",
			"shape": "1",
			"color": "3",
			"expected_label": "zeteeckoh",
			"input_label": "zeteeckoh",
			"response_time": 4441,
			"time": 1683213723
		},
		{
			"test_type": "test_comprehension",
			"word": "buvykow",
			"items": [
				"0_2"
			],
			"array": [
				"3_2",
				"1_0",
				"1_3",
				"2_2",
				"0_0",
				"0_1",
				"2_3",
				"2_1",
				"1_2",
				"3_1",
				"2_0",
				"3_3",
				"1_1",
				"0_3",
				"0_2",
				"3_0"
			],
			"selected_button": 14,
			"selected_item": "0_2",
			"response_time": 4288,
			"time": 1683213729
		},
		{
			"test_type": "test_production",
			"shape": "2",
			"color": "2",
			"expected_label": "gafykoe",
			"input_label": "gafykoe",
			"response_time": 3268,
			"time": 1683213734
		},
		{
			"test_type": "test_comprehension",
			"word": "wopyckoe",
			"items": [
				"3_2"
			],
			"array": [
				"2_0",
				"1_0",
				"0_1",
				"2_3",
				"0_3",
				"3_3",
				"1_1",
				"3_1",
				"0_2",
				"1_3",
				"0_0",
				"3_0",
				"1_2",
				"3_2",
				"2_1",
				"2_2"
			],
			"selected_button": 11,
			"selected_item": "3_0",
			"response_time": 7929,
			"time": 1683213743
		},
		{
			"test_type": "test_production",
			"shape": "2",
			"color": "0",
			"expected_label": "gafeecow",
			"input_label": "gafeecow",
			"response_time": 3359,
			"time": 1683213748
		},
		{
			"test_type": "test_comprehension",
			"word": "buvecow",
			"items": [
				"0_0"
			],
			"array": [
				"2_0",
				"1_2",
				"3_2",
				"1_0",
				"0_3",
				"2_1",
				"2_3",
				"3_1",
				"1_3",
				"0_1",
				"0_0",
				"3_3",
				"0_2",
				"1_1",
				"2_2",
				"3_0"
			],
			"selected_button": 10,
			"selected_item": "0_0",
			"response_time": 10208,
			"time": 1683213760
		},
		{
			"test_type": "test_production",
			"shape": "1",
			"color": "0",
			"expected_label": "zetickoe",
			"input_label": "zetickoe",
			"response_time": 3116,
			"time": 1683213765
		},
		{
			"test_type": "test_comprehension",
			"word": "zetickoe",
			"items": [
				"1_0"
			],
			"array": [
				"2_0",
				"1_3",
				"0_1",
				"1_2",
				"2_3",
				"1_0",
				"1_1",
				"0_2",
				"2_2",
				"0_0",
				"3_3",
				"3_1",
				"3_2",
				"3_0",
				"0_3",
				"2_1"
			],
			"selected_button": 5,
			"selected_item": "1_0",
			"response_time": 2179,
			"time": 1683213768
		},
		{
			"test_type": "test_production",
			"shape": "3",
			"color": "0",
			"expected_label": "wopickoe",
			"input_label": "wopickoe",
			"response_time": 5481,
			"time": 1683213775
		},
		{
			"test_type": "test_comprehension",
			"word": "gafykoe",
			"items": [
				"2_2"
			],
			"array": [
				"3_0",
				"2_3",
				"0_3",
				"0_1",
				"0_0",
				"2_0",
				"2_2",
				"2_1",
				"3_1",
				"1_2",
				"1_3",
				"1_0",
				"3_2",
				"0_2",
				"3_3",
				"1_1"
			],
			"selected_button": 6,
			"selected_item": "2_2",
			"response_time": 12248,
			"time": 1683213789
		},
		{
			"test_type": "test_production",
			"shape": "3",
			"color": "3",
			"expected_label": "wopikoh",
			"input_label": "wopikoh",
			"response_time": 4701,
			"time": 1683213795
		},
		{
			"test_type": "test_comprehension",
			"word": "buvyckow",
			"items": [
				"0_3"
			],
			"array": [
				"2_0",
				"1_3",
				"1_2",
				"3_1",
				"0_1",
				"2_2",
				"3_2",
				"1_1",
				"2_3",
				"2_1",
				"3_0",
				"0_2",
				"0_3",
				"1_0",
				"0_0",
				"3_3"
			],
			"selected_button": 11,
			"selected_item": "0_2",
			"response_time": 2806,
			"time": 1683213800
		},
		{
			"test_type": "test_production",
			"shape": "3",
			"color": "2",
			"expected_label": "wopyckoe",
			"input_label": "wopickoe",
			"response_time": 5508,
			"time": 1683213807
		},
		{
			"test_type": "test_comprehension",
			"word": "gafeecoh",
			"items": [
				"2_1"
			],
			"array": [
				"0_3",
				"3_2",
				"2_2",
				"1_3",
				"3_1",
				"0_0",
				"2_0",
				"1_2",
				"2_1",
				"0_2",
				"3_0",
				"2_3",
				"1_1",
				"3_3",
				"0_1",
				"1_0"
			],
			"selected_button": 8,
			"selected_item": "2_1",
			"response_time": 9094,
			"time": 1683213818
		},
		{
			"test_type": "test_production",
			"shape": "2",
			"color": "3",
			"expected_label": "gafeeckoh",
			"input_label": "gafikoh",
			"response_time": 11263,
			"time": 1683213830
		},
		{
			"test_type": "test_comprehension",
			"word": "gafeeckoh",
			"items": [
				"2_3"
			],
			"array": [
				"2_2",
				"1_1",
				"2_0",
				"1_2",
				"1_0",
				"3_3",
				"2_1",
				"0_2",
				"0_3",
				"3_0",
				"2_3",
				"0_0",
				"3_1",
				"1_3",
				"0_1",
				"3_2"
			],
			"selected_button": 10,
			"selected_item": "2_3",
			"response_time": 2014,
			"time": 1683213834
		},
		{
			"test_type": "test_production",
			"shape": "0",
			"color": "0",
			"expected_label": "buvecow",
			"input_label": "buvikohe",
			"response_time": 3981,
			"time": 1683213840
		},
		{
			"test_type": "test_comprehension",
			"word": "wopikoh",
			"items": [
				"3_3"
			],
			"array": [
				"0_3",
				"2_1",
				"3_0",
				"1_3",
				"2_3",
				"2_0",
				"2_2",
				"3_3",
				"3_1",
				"0_2",
				"1_0",
				"0_0",
				"3_2",
				"0_1",
				"1_2",
				"1_1"
			],
			"selected_button": 7,
			"selected_item": "3_3",
			"response_time": 8109,
			"time": 1683213849
		},
		{
			"test_type": "test_production",
			"shape": "1",
			"color": "1",
			"expected_label": "zeteecoe",
			"input_label": "zeteecoe",
			"response_time": 5020,
			"time": 1683213856
		},
		{
			"test_type": "test_comprehension",
			"word": "gafeecow",
			"items": [
				"2_0"
			],
			"array": [
				"0_2",
				"2_2",
				"1_2",
				"3_0",
				"2_3",
				"2_0",
				"1_0",
				"3_3",
				"0_0",
				"3_1",
				"0_3",
				"1_1",
				"1_3",
				"3_2",
				"2_1",
				"0_1"
			],
			"selected_button": 5,
			"selected_item": "2_0",
			"response_time": 2639,
			"time": 1683213860
		}
	],
	"comments": "I just \"save\" everything in my head. It was difficult task",
	"lexicon": {
		"0_0": "buvikohe",
		"0_1": "buvikow",
		"0_2": "buvikoe",
		"0_3": "buvyckow",
		"1_0": "zetickoe",
		"1_1": "zeteecoe",
		"1_2": "zeteekow",
		"1_3": "zeteeckoh",
		"2_0": "gafeecow",
		"2_1": "gafeecoh",
		"2_2": "gafykoe",
		"2_3": "gafikoh",
		"3_0": "wopickoe",
		"3_1": "wopeeckoe",
		"3_2": "wopickoe",
		"3_3": "wopikoh"
	}
}